[
  {
    "_id": "6a1feb3cf931bcff1af5ca9b",
    "employeeId": "6a1d1e3371523c75c540fb5d",
    "year": 2026,
    "month": 5,
    "__v": 0,
    "createdAt": "2026-06-03T08:52:12.088Z",
    "isFallback": false,
    "reason": "Perfect Attendance: 0 PSL, 0 Half-Days, 0 LWP",
    "tier": 1,
    "updatedAt": "2026-06-13T06:43:26.145Z"
  },
  {
    "_id": "6a1feb3df931bcff1af5caa4",
    "month": 5,
    "employeeId": "6a1fcba29f42d83bb7635f86",
    "year": 2026,
    "__v": 0,
    "createdAt": "2026-06-03T08:52:13.169Z",
    "isFallback": false,
    "reason": "Triggered by exceeding 1 PSL absence equivalent (2 PSL, 0 Half-Days, total equivalent: 2 days)",
    "tier": 3,
    "updatedAt": "2026-06-13T06:43:26.998Z"
  },
  {
    "_id": "6a1feb67f931bcff1af5cab2",
    "employeeId": "6a1d1e3171523c75c540fb4d",
    "year": 2026,
    "month": 4,
    "__v": 0,
    "createdAt": "2026-06-03T08:52:54.963Z",
    "isFallback": false,
    "reason": "Perfect Attendance: 0 PSL, 0 Half-Days, 0 LWP",
    "tier": 1,
    "updatedAt": "2026-06-04T11:19:00.307Z"
  },
  {
    "_id": "6a2121904deac4a7e0284ac5",
    "employeeId": "6a200820311c45376c8e6bd9",
    "year": 2026,
    "month": 5,
    "__v": 0,
    "createdAt": "2026-06-04T06:56:16.692Z",
    "isFallback": false,
    "reason": "Satisfactory Attendance within 1 PSL equivalent: 0 PSL, 1 Half-Days (total equivalent: 0.5 days)",
    "tier": 2,
    "updatedAt": "2026-06-13T06:43:28.972Z"
  },
  {
    "_id": "6a2121a34deac4a7e0284afb",
    "employeeId": "6a210b329e4df9a820c230c2",
    "year": 2026,
    "month": 5,
    "__v": 0,
    "createdAt": "2026-06-04T06:56:35.189Z",
    "isFallback": false,
    "reason": "Perfect Attendance: 0 PSL, 0 Half-Days, 0 LWP",
    "tier": 1,
    "updatedAt": "2026-06-13T06:43:38.475Z"
  },
  {
    "_id": "6a2121a34deac4a7e0284afd",
    "month": 5,
    "year": 2026,
    "employeeId": "6a210b709e4df9a820c230cb",
    "__v": 0,
    "createdAt": "2026-06-04T06:56:35.733Z",
    "isFallback": false,
    "reason": "Perfect Attendance: 0 PSL, 0 Half-Days, 0 LWP",
    "tier": 1,
    "updatedAt": "2026-06-13T06:43:38.781Z"
  },
  {
    "_id": "6a2121b84deac4a7e0284b31",
    "month": 4,
    "employeeId": "6a2016e9779aee60f9a25c08",
    "year": 2026,
    "__v": 0,
    "createdAt": "2026-06-04T06:56:55.955Z",
    "isFallback": false,
    "reason": "Perfect Attendance: 0 PSL, 0 Half-Days, 0 LWP",
    "tier": 1,
    "updatedAt": "2026-06-04T11:19:51.343Z"
  },
  {
    "_id": "6a2121bb4deac4a7e0284b3f",
    "employeeId": "6a201c29779aee60f9a25edc",
    "month": 4,
    "year": 2026,
    "__v": 0,
    "createdAt": "2026-06-04T06:56:59.765Z",
    "isFallback": false,
    "reason": "Triggered by Leave Without Pay (1 LWP days)",
    "tier": 3,
    "updatedAt": "2026-06-04T11:20:01.313Z"
  },
  {
    "_id": "6a2121c34deac4a7e0284b57",
    "month": 4,
    "year": 2026,
    "employeeId": "6a201f339e4df9a820c22627",
    "__v": 0,
    "createdAt": "2026-06-04T06:57:07.057Z",
    "isFallback": false,
    "reason": "Perfect Attendance: 0 PSL, 0 Half-Days, 0 LWP",
    "tier": 1,
    "updatedAt": "2026-06-04T11:20:15.947Z"
  },
  {
    "_id": "6a213eb64deac4a7e0284c18",
    "employeeId": "6a2129579e4df9a820c23444",
    "month": 4,
    "year": 2026,
    "__v": 0,
    "createdAt": "2026-06-04T09:00:38.729Z",
    "isFallback": false,
    "reason": "Perfect Attendance: 0 PSL, 0 Half-Days, 0 LWP",
    "tier": 1,
    "updatedAt": "2026-06-04T11:20:41.972Z"
  },
  {
    "_id": "6a21585e4deac4a7e0284dd6",
    "employeeId": "6a21528f453d791e72eae17b",
    "year": 2026,
    "month": 5,
    "__v": 0,
    "createdAt": "2026-06-04T10:50:06.141Z",
    "isFallback": false,
    "reason": "Perfect Attendance: 0 PSL, 0 Half-Days, 0 LWP",
    "tier": 1,
    "updatedAt": "2026-06-13T06:43:43.065Z"
  },
  {
    "_id": "6a1fca9ef931bcff1af5c48e",
    "employeeId": "6a1d1e3171523c75c540fb45",
    "year": 2026,
    "month": 5,
    "__v": 0,
    "createdAt": "2026-06-03T06:33:02.527Z",
    "isFallback": false,
    "reason": "Perfect Attendance: 0 PSL, 0 Half-Days, 0 LWP",
    "tier": 1,
    "updatedAt": "2026-06-03T07:08:52.618Z"
  },
  {
    "_id": "6a21219c4deac4a7e0284ae7",
    "employeeId": "6a201e189e4df9a820c22535",
    "year": 2026,
    "month": 5,
    "__v": 0,
    "createdAt": "2026-06-04T06:56:28.489Z",
    "isFallback": false,
    "reason": "Perfect Attendance: 0 PSL, 0 Half-Days, 0 LWP",
    "tier": 1,
    "updatedAt": "2026-06-13T06:43:35.161Z"
  },
  {
    "_id": "6a2121a74deac4a7e0284b07",
    "employeeId": "6a210c869e4df9a820c2311a",
    "year": 2026,
    "month": 5,
    "__v": 0,
    "createdAt": "2026-06-04T06:56:38.882Z",
    "isFallback": false,
    "reason": "Triggered by Leave Without Pay (2 LWP days)",
    "tier": 3,
    "updatedAt": "2026-06-13T06:43:40.202Z"
  },
  {
    "_id": "6a2121ab4deac4a7e0284b17",
    "employeeId": "6a2119599e4df9a820c23377",
    "year": 2026,
    "month": 5,
    "__v": 0,
    "createdAt": "2026-06-04T06:56:43.753Z",
    "isFallback": false,
    "reason": "Triggered by Leave Without Pay (3 LWP days)",
    "tier": 3,
    "updatedAt": "2026-06-13T06:43:42.490Z"
  },
  {
    "_id": "6a2121b24deac4a7e0284b21",
    "employeeId": "6a200820311c45376c8e6bd9",
    "month": 4,
    "year": 2026,
    "__v": 0,
    "createdAt": "2026-06-04T06:56:50.402Z",
    "isFallback": false,
    "reason": "Perfect Attendance: 0 PSL, 0 Half-Days, 0 LWP",
    "tier": 1,
    "updatedAt": "2026-06-04T11:19:38.821Z"
  },
  {
    "_id": "6a2121b64deac4a7e0284b2d",
    "employeeId": "6a2015e0779aee60f9a25b95",
    "year": 2026,
    "month": 4,
    "__v": 0,
    "createdAt": "2026-06-04T06:56:54.858Z",
    "isFallback": false,
    "reason": "Perfect Attendance: 0 PSL, 0 Half-Days, 0 LWP",
    "tier": 1,
    "updatedAt": "2026-06-04T11:19:48.968Z"
  },
  {
    "_id": "6a2121bd4deac4a7e0284b43",
    "employeeId": "6a201cc9779aee60f9a25fc1",
    "year": 2026,
    "month": 4,
    "__v": 0,
    "createdAt": "2026-06-04T06:57:01.084Z",
    "isFallback": false,
    "reason": "Triggered by Leave Without Pay (1 LWP days)",
    "tier": 3,
    "updatedAt": "2026-06-04T11:20:03.843Z"
  },
  {
    "_id": "6a2121c04deac4a7e0284b4d",
    "month": 4,
    "year": 2026,
    "employeeId": "6a201e189e4df9a820c22535",
    "__v": 0,
    "createdAt": "2026-06-04T06:57:03.938Z",
    "isFallback": false,
    "reason": "Satisfactory Attendance within 1 PSL equivalent: 1 PSL, 0 Half-Days (total equivalent: 1 days)",
    "tier": 2,
    "updatedAt": "2026-06-04T11:20:10.093Z"
  },
  {
    "_id": "6a2121c44deac4a7e0284b5d",
    "month": 4,
    "employeeId": "6a2107b79e4df9a820c22ee8",
    "year": 2026,
    "__v": 0,
    "createdAt": "2026-06-04T06:57:08.782Z",
    "isFallback": false,
    "reason": "Satisfactory Attendance within 1 PSL equivalent: 1 PSL, 0 Half-Days (total equivalent: 1 days)",
    "tier": 2,
    "updatedAt": "2026-06-04T11:20:19.463Z"
  },
  {
    "_id": "6a1fd4e9f931bcff1af5c770",
    "employeeId": "6a1fd4ce9f42d83bb763668c",
    "year": 2026,
    "month": 5,
    "__v": 0,
    "createdAt": "2026-06-03T07:16:57.899Z",
    "isFallback": false,
    "reason": "Perfect Attendance: 0 PSL, 0 Half-Days, 0 LWP",
    "tier": 1,
    "updatedAt": "2026-06-13T06:43:27.292Z"
  },
  {
    "_id": "6a1feb3cf931bcff1af5caa1",
    "month": 5,
    "employeeId": "6a1fcb409f42d83bb7635f57",
    "year": 2026,
    "__v": 0,
    "createdAt": "2026-06-03T08:52:12.739Z",
    "isFallback": false,
    "reason": "Perfect Attendance: 0 PSL, 0 Half-Days, 0 LWP",
    "tier": 1,
    "updatedAt": "2026-06-13T06:43:26.710Z"
  },
  {
    "_id": "6a1feb68f931bcff1af5cabc",
    "employeeId": "6a1d1e3371523c75c540fb61",
    "month": 4,
    "year": 2026,
    "__v": 0,
    "createdAt": "2026-06-03T08:52:56.306Z",
    "isFallback": false,
    "reason": "Perfect Attendance: 0 PSL, 0 Half-Days, 0 LWP",
    "tier": 1,
    "updatedAt": "2026-06-05T05:39:29.055Z"
  },
  {
    "_id": "6a21218f4deac4a7e0284ac1",
    "employeeId": "6a20052a311c45376c8e6b78",
    "month": 5,
    "year": 2026,
    "__v": 0,
    "createdAt": "2026-06-04T06:56:15.511Z",
    "isFallback": false,
    "reason": "Perfect Attendance: 0 PSL, 0 Half-Days, 0 LWP",
    "tier": 1,
    "updatedAt": "2026-06-13T06:43:28.405Z"
  },
  {
    "_id": "6a2121914deac4a7e0284ac7",
    "month": 5,
    "employeeId": "6a20089f311c45376c8e6be2",
    "year": 2026,
    "__v": 0,
    "createdAt": "2026-06-04T06:56:17.330Z",
    "isFallback": false,
    "reason": "Perfect Attendance: 0 PSL, 0 Half-Days, 0 LWP",
    "tier": 1,
    "updatedAt": "2026-06-13T06:43:29.254Z"
  },
  {
    "_id": "6a2121934deac4a7e0284acd",
    "month": 5,
    "employeeId": "6a20154d779aee60f9a25b8c",
    "year": 2026,
    "__v": 0,
    "createdAt": "2026-06-04T06:56:19.030Z",
    "isFallback": false,
    "reason": "Perfect Attendance: 0 PSL, 0 Half-Days, 0 LWP",
    "tier": 1,
    "updatedAt": "2026-06-13T06:43:30.397Z"
  },
  {
    "_id": "6a2121994deac4a7e0284adf",
    "employeeId": "6a201c55779aee60f9a25f46",
    "year": 2026,
    "month": 5,
    "__v": 0,
    "createdAt": "2026-06-04T06:56:25.794Z",
    "isFallback": false,
    "reason": "Perfect Attendance: 0 PSL, 0 Half-Days, 0 LWP",
    "tier": 1,
    "updatedAt": "2026-06-13T06:43:33.502Z"
  },
  {
    "_id": "6a2121b94deac4a7e0284b35",
    "employeeId": "6a20189d779aee60f9a25c1a",
    "year": 2026,
    "month": 4,
    "__v": 0,
    "createdAt": "2026-06-04T06:56:56.998Z",
    "isFallback": false,
    "reason": "Perfect Attendance: 0 PSL, 0 Half-Days, 0 LWP",
    "tier": 1,
    "updatedAt": "2026-06-04T11:19:54.086Z"
  },
  {
    "_id": "6a2121cb4deac4a7e0284b73",
    "employeeId": "6a210ca19e4df9a820c2312f",
    "year": 2026,
    "month": 4,
    "__v": 0,
    "createdAt": "2026-06-04T06:57:15.084Z",
    "isFallback": false,
    "reason": "Triggered by exceeding 1 PSL absence equivalent (1 PSL, 1 Half-Days, total equivalent: 1.5 days)",
    "tier": 3,
    "updatedAt": "2026-06-04T11:20:32.380Z"
  },
  {
    "_id": "6a2121cc4deac4a7e0284b77",
    "employeeId": "6a210d579e4df9a820c231c3",
    "month": 4,
    "year": 2026,
    "__v": 0,
    "createdAt": "2026-06-04T06:57:16.315Z",
    "isFallback": false,
    "reason": "Triggered by Leave Without Pay (1 LWP days)",
    "tier": 3,
    "updatedAt": "2026-06-04T11:20:34.840Z"
  },
  {
    "_id": "6a2121cd4deac4a7e0284b7b",
    "month": 4,
    "year": 2026,
    "employeeId": "6a210da89e4df9a820c231e1",
    "__v": 0,
    "createdAt": "2026-06-04T06:57:17.640Z",
    "isFallback": false,
    "reason": "Satisfactory Attendance within 1 PSL equivalent: 0 PSL, 1 Half-Days (total equivalent: 0.5 days)",
    "tier": 2,
    "updatedAt": "2026-06-04T11:20:37.161Z"
  },
  {
    "_id": "6a213eaf4deac4a7e0284c16",
    "employeeId": "6a2129579e4df9a820c23444",
    "month": 5,
    "year": 2026,
    "__v": 0,
    "createdAt": "2026-06-04T09:00:30.939Z",
    "isFallback": false,
    "reason": "Perfect Attendance: 0 PSL, 0 Half-Days, 0 LWP",
    "tier": 1,
    "updatedAt": "2026-06-13T06:43:42.776Z"
  },
  {
    "_id": "6a2265df4deac4a7e028539a",
    "employeeId": "6a2264afe30358b77365b103",
    "year": 2026,
    "month": 5,
    "__v": 0,
    "createdAt": "2026-06-05T05:59:59.786Z",
    "isFallback": false,
    "reason": "Triggered by Leave Without Pay (1 LWP days)",
    "tier": 3,
    "updatedAt": "2026-06-13T06:43:43.963Z"
  },
  {
    "_id": "6a1feb39f931bcff1af5ca86",
    "month": 5,
    "year": 2026,
    "employeeId": "6a1d1e3071523c75c540fb3d",
    "__v": 0,
    "createdAt": "2026-06-03T08:52:09.461Z",
    "isFallback": false,
    "reason": "Perfect Attendance: 0 PSL, 0 Half-Days, 0 LWP",
    "tier": 1,
    "updatedAt": "2026-06-13T06:43:24.198Z"
  },
  {
    "_id": "6a1feb3bf931bcff1af5ca98",
    "month": 5,
    "year": 2026,
    "employeeId": "6a1d1e3271523c75c540fb59",
    "__v": 0,
    "createdAt": "2026-06-03T08:52:11.684Z",
    "isFallback": false,
    "reason": "Satisfactory Attendance within 1 PSL equivalent: 0 PSL, 1 Half-Days (total equivalent: 0.5 days)",
    "tier": 2,
    "updatedAt": "2026-06-13T06:43:25.865Z"
  },
  {
    "_id": "6a1feb65f931bcff1af5caa8",
    "employeeId": "6a1d1e2f71523c75c540fb35",
    "month": 4,
    "year": 2026,
    "__v": 0,
    "createdAt": "2026-06-03T08:52:53.655Z",
    "isFallback": false,
    "reason": "Triggered by Leave Without Pay (1 LWP days)",
    "tier": 3,
    "updatedAt": "2026-06-05T05:46:07.998Z"
  },
  {
    "_id": "6a1feb66f931bcff1af5cab0",
    "month": 4,
    "employeeId": "6a1d1e3171523c75c540fb49",
    "year": 2026,
    "__v": 0,
    "createdAt": "2026-06-03T08:52:54.682Z",
    "isFallback": false,
    "reason": "Triggered by Leave Without Pay (2 LWP days)",
    "tier": 3,
    "updatedAt": "2026-06-04T11:18:55.765Z"
  },
  {
    "_id": "6a20ffe64deac4a7e0284859",
    "employeeId": "6a201c29779aee60f9a25edc",
    "year": 2026,
    "month": 5,
    "__v": 0,
    "createdAt": "2026-06-04T04:32:38.068Z",
    "isFallback": false,
    "reason": "Perfect Attendance: 0 PSL, 0 Half-Days, 0 LWP",
    "tier": 1,
    "updatedAt": "2026-06-13T06:43:33.185Z"
  },
  {
    "_id": "6a2121964deac4a7e0284ad5",
    "employeeId": "6a2017ee779aee60f9a25c11",
    "year": 2026,
    "month": 5,
    "__v": 0,
    "createdAt": "2026-06-04T06:56:21.965Z",
    "isFallback": false,
    "reason": "Perfect Attendance: 0 PSL, 0 Half-Days, 0 LWP",
    "tier": 1,
    "updatedAt": "2026-06-13T06:43:31.523Z"
  },
  {
    "_id": "6a2121984deac4a7e0284adb",
    "month": 5,
    "employeeId": "6a201bf9779aee60f9a25e42",
    "year": 2026,
    "__v": 0,
    "createdAt": "2026-06-04T06:56:24.339Z",
    "isFallback": false,
    "reason": "Satisfactory Attendance within 1 PSL equivalent: 1 PSL, 0 Half-Days (total equivalent: 1 days)",
    "tier": 2,
    "updatedAt": "2026-06-13T06:43:32.614Z"
  },
  {
    "_id": "6a2121a94deac4a7e0284b11",
    "month": 5,
    "employeeId": "6a210da89e4df9a820c231e1",
    "year": 2026,
    "__v": 0,
    "createdAt": "2026-06-04T06:56:41.786Z",
    "isFallback": false,
    "reason": "Satisfactory Attendance within 1 PSL equivalent: 0 PSL, 1 Half-Days (total equivalent: 0.5 days)",
    "tier": 2,
    "updatedAt": "2026-06-13T06:43:41.629Z"
  },
  {
    "_id": "6a2121b64deac4a7e0284b2b",
    "month": 4,
    "year": 2026,
    "employeeId": "6a20154d779aee60f9a25b8c",
    "__v": 0,
    "createdAt": "2026-06-04T06:56:54.071Z",
    "isFallback": false,
    "reason": "Triggered by exceeding 1 PSL absence equivalent (1 PSL, 1 Half-Days, total equivalent: 1.5 days)",
    "tier": 3,
    "updatedAt": "2026-06-04T11:19:47.318Z"
  },
  {
    "_id": "6a21219e4deac4a7e0284aef",
    "month": 5,
    "employeeId": "6a201f339e4df9a820c22627",
    "year": 2026,
    "__v": 0,
    "createdAt": "2026-06-04T06:56:30.815Z",
    "isFallback": false,
    "reason": "Perfect Attendance: 0 PSL, 0 Half-Days, 0 LWP",
    "tier": 1,
    "updatedAt": "2026-06-13T06:43:36.479Z"
  },
  {
    "_id": "6a2121a24deac4a7e0284af9",
    "month": 5,
    "year": 2026,
    "employeeId": "6a210b1e9e4df9a820c230b9",
    "__v": 0,
    "createdAt": "2026-06-04T06:56:34.563Z",
    "isFallback": false,
    "reason": "Satisfactory Attendance within 1 PSL equivalent: 0 PSL, 1 Half-Days (total equivalent: 0.5 days)",
    "tier": 2,
    "updatedAt": "2026-06-13T06:43:38.199Z"
  },
  {
    "_id": "6a2121a74deac4a7e0284b09",
    "month": 5,
    "year": 2026,
    "employeeId": "6a210ca19e4df9a820c2312f",
    "__v": 0,
    "createdAt": "2026-06-04T06:56:39.554Z",
    "isFallback": false,
    "reason": "Triggered by Leave Without Pay (5 LWP days)",
    "tier": 3,
    "updatedAt": "2026-06-13T06:43:40.496Z"
  },
  {
    "_id": "6a2121a94deac4a7e0284b0f",
    "employeeId": "6a210d5a9e4df9a820c231cc",
    "month": 5,
    "year": 2026,
    "__v": 0,
    "createdAt": "2026-06-04T06:56:41.211Z",
    "isFallback": false,
    "reason": "Satisfactory Attendance within 1 PSL equivalent: 1 PSL, 0 Half-Days (total equivalent: 1 days)",
    "tier": 2,
    "updatedAt": "2026-06-13T06:43:41.348Z"
  },
  {
    "_id": "6a2121bc4deac4a7e0284b41",
    "month": 4,
    "year": 2026,
    "employeeId": "6a201c55779aee60f9a25f46",
    "__v": 0,
    "createdAt": "2026-06-04T06:57:00.553Z",
    "isFallback": false,
    "reason": "Triggered by Leave Without Pay (1 LWP days)",
    "tier": 3,
    "updatedAt": "2026-06-04T11:20:02.619Z"
  },
  {
    "_id": "6a2121c64deac4a7e0284b63",
    "month": 4,
    "employeeId": "6a210b1e9e4df9a820c230b9",
    "year": 2026,
    "__v": 0,
    "createdAt": "2026-06-04T06:57:10.371Z",
    "isFallback": false,
    "reason": "Satisfactory Attendance within 1 PSL equivalent: 0 PSL, 2 Half-Days (total equivalent: 1 days)",
    "tier": 2,
    "updatedAt": "2026-06-04T11:20:22.882Z"
  },
  {
    "_id": "6a1feb38f931bcff1af5ca7e",
    "employeeId": "6a1d1e2e71523c75c540fb31",
    "year": 2026,
    "month": 5,
    "__v": 0,
    "createdAt": "2026-06-03T08:52:08.353Z",
    "isFallback": false,
    "reason": "Perfect Attendance: 0 PSL, 0 Half-Days, 0 LWP",
    "tier": 1,
    "updatedAt": "2026-06-13T06:43:23.326Z"
  },
  {
    "_id": "6a1feb39f931bcff1af5ca89",
    "employeeId": "6a1d1e3071523c75c540fb41",
    "year": 2026,
    "month": 5,
    "__v": 0,
    "createdAt": "2026-06-03T08:52:09.804Z",
    "isFallback": false,
    "reason": "Perfect Attendance: 0 PSL, 0 Half-Days, 0 LWP",
    "tier": 1,
    "updatedAt": "2026-06-13T06:43:24.478Z"
  },
  {
    "_id": "6a1feb3bf931bcff1af5ca95",
    "employeeId": "6a1d1e3271523c75c540fb55",
    "month": 5,
    "year": 2026,
    "__v": 0,
    "createdAt": "2026-06-03T08:52:11.349Z",
    "isFallback": false,
    "reason": "Perfect Attendance: 0 PSL, 0 Half-Days, 0 LWP",
    "tier": 1,
    "updatedAt": "2026-06-13T06:43:25.583Z"
  },
  {
    "_id": "6a1feb66f931bcff1af5caaa",
    "employeeId": "6a1d1e3071523c75c540fb39",
    "year": 2026,
    "month": 4,
    "__v": 0,
    "createdAt": "2026-06-03T08:52:53.899Z",
    "isFallback": false,
    "reason": "Perfect Attendance: 0 PSL, 0 Half-Days, 0 LWP",
    "tier": 1,
    "updatedAt": "2026-06-05T04:20:09.349Z"
  },
  {
    "_id": "6a2121944deac4a7e0284ad1",
    "month": 5,
    "year": 2026,
    "employeeId": "6a20168d779aee60f9a25b9e",
    "__v": 0,
    "createdAt": "2026-06-04T06:56:20.572Z",
    "isFallback": false,
    "reason": "Perfect Attendance: 0 PSL, 0 Half-Days, 0 LWP",
    "tier": 1,
    "updatedAt": "2026-06-13T06:43:30.969Z"
  },
  {
    "_id": "6a2121974deac4a7e0284ad9",
    "month": 5,
    "employeeId": "6a201b0d779aee60f9a25cc7",
    "year": 2026,
    "__v": 0,
    "createdAt": "2026-06-04T06:56:23.547Z",
    "isFallback": false,
    "reason": "Perfect Attendance: 0 PSL, 0 Half-Days, 0 LWP",
    "tier": 1,
    "updatedAt": "2026-06-13T06:43:32.067Z"
  },
  {
    "_id": "6a2121b44deac4a7e0284b27",
    "employeeId": "6a200a57311c45376c8e6bf4",
    "year": 2026,
    "month": 4,
    "__v": 0,
    "createdAt": "2026-06-04T06:56:52.522Z",
    "isFallback": false,
    "reason": "Perfect Attendance: 0 PSL, 0 Half-Days, 0 LWP",
    "tier": 1,
    "updatedAt": "2026-06-04T11:19:44.379Z"
  },
  {
    "_id": "6a2168eb4deac4a7e0284f0b",
    "employeeId": "6a2164791d3fe393896fe5e9",
    "year": 2026,
    "month": 5,
    "__v": 0,
    "createdAt": "2026-06-04T12:00:43.365Z",
    "isFallback": false,
    "reason": "Perfect Attendance: 0 PSL, 0 Half-Days, 0 LWP",
    "tier": 1,
    "updatedAt": "2026-06-13T06:43:43.680Z"
  },
  {
    "_id": "6a2265294deac4a7e0285394",
    "employeeId": "6a2264afe30358b77365b103",
    "month": 3,
    "year": 2026,
    "__v": 0,
    "createdAt": "2026-06-05T05:56:57.490Z",
    "isFallback": false,
    "reason": "Satisfactory Attendance within 1 PSL equivalent: 1 PSL, 0 Half-Days (total equivalent: 1 days)",
    "tier": 2,
    "updatedAt": "2026-06-05T05:56:57.490Z"
  },
  {
    "_id": "6a1feb3bf931bcff1af5ca92",
    "month": 5,
    "employeeId": "6a1d1e3271523c75c540fb51",
    "year": 2026,
    "__v": 0,
    "createdAt": "2026-06-03T08:52:11.012Z",
    "isFallback": false,
    "reason": "Triggered by exceeding 1 PSL absence equivalent (1 PSL, 1 Half-Days, total equivalent: 1.5 days)",
    "tier": 3,
    "updatedAt": "2026-06-13T06:43:25.307Z"
  },
  {
    "_id": "6a1feb3cf931bcff1af5ca9e",
    "month": 5,
    "year": 2026,
    "employeeId": "6a1d1e3371523c75c540fb61",
    "__v": 0,
    "createdAt": "2026-06-03T08:52:12.414Z",
    "isFallback": false,
    "reason": "Satisfactory Attendance within 1 PSL equivalent: 0 PSL, 1 Half-Days (total equivalent: 0.5 days)",
    "tier": 2,
    "updatedAt": "2026-06-13T06:43:26.425Z"
  },
  {
    "_id": "6a1feb65f931bcff1af5caa6",
    "employeeId": "6a1d1e2e71523c75c540fb31",
    "month": 4,
    "year": 2026,
    "__v": 0,
    "createdAt": "2026-06-03T08:52:53.427Z",
    "isFallback": false,
    "reason": "Perfect Attendance: 0 PSL, 0 Half-Days, 0 LWP",
    "tier": 1,
    "updatedAt": "2026-06-04T11:18:39.869Z"
  },
  {
    "_id": "6a20ffbb4deac4a7e0284854",
    "month": 5,
    "year": 2026,
    "employeeId": "6a201e289e4df9a820c22540",
    "__v": 0,
    "createdAt": "2026-06-04T04:31:55.230Z",
    "isFallback": false,
    "reason": "Satisfactory Attendance within 1 PSL equivalent: 1 PSL, 0 Half-Days (total equivalent: 1 days)",
    "tier": 2,
    "updatedAt": "2026-06-13T06:43:35.426Z"
  },
  {
    "_id": "6a2106ee4deac4a7e02848ea",
    "month": 5,
    "year": 2026,
    "employeeId": "6a2013b8943b2ce58f2ba723",
    "__v": 0,
    "createdAt": "2026-06-04T05:02:38.816Z",
    "isFallback": false,
    "reason": "Satisfactory Attendance within 1 PSL equivalent: 1 PSL, 0 Half-Days (total equivalent: 1 days)",
    "tier": 2,
    "updatedAt": "2026-06-13T06:43:30.106Z"
  },
  {
    "_id": "6a2121974deac4a7e0284ad7",
    "month": 5,
    "year": 2026,
    "employeeId": "6a20189d779aee60f9a25c1a",
    "__v": 0,
    "createdAt": "2026-06-04T06:56:22.932Z",
    "isFallback": false,
    "reason": "Perfect Attendance: 0 PSL, 0 Half-Days, 0 LWP",
    "tier": 1,
    "updatedAt": "2026-06-13T06:43:31.793Z"
  },
  {
    "_id": "6a2121a64deac4a7e0284b05",
    "month": 5,
    "employeeId": "6a210c699e4df9a820c23111",
    "year": 2026,
    "__v": 0,
    "createdAt": "2026-06-04T06:56:38.263Z",
    "isFallback": false,
    "reason": "Perfect Attendance: 0 PSL, 0 Half-Days, 0 LWP",
    "tier": 1,
    "updatedAt": "2026-06-13T06:43:39.920Z"
  },
  {
    "_id": "6a2121c14deac4a7e0284b51",
    "employeeId": "6a201e779e4df9a820c225a8",
    "year": 2026,
    "month": 4,
    "__v": 0,
    "createdAt": "2026-06-04T06:57:04.991Z",
    "isFallback": false,
    "reason": "Perfect Attendance: 0 PSL, 0 Half-Days, 0 LWP",
    "tier": 1,
    "updatedAt": "2026-06-04T11:20:12.451Z"
  },
  {
    "_id": "6a2121c34deac4a7e0284b59",
    "employeeId": "6a20584d9e4df9a820c22ab5",
    "month": 4,
    "year": 2026,
    "__v": 0,
    "createdAt": "2026-06-04T06:57:07.591Z",
    "isFallback": false,
    "reason": "Satisfactory Attendance within 1 PSL equivalent: 1 PSL, 0 Half-Days (total equivalent: 1 days)",
    "tier": 2,
    "updatedAt": "2026-06-04T11:20:17.118Z"
  },
  {
    "_id": "6a2121c94deac4a7e0284b6d",
    "month": 4,
    "year": 2026,
    "employeeId": "6a210c199e4df9a820c23108",
    "__v": 0,
    "createdAt": "2026-06-04T06:57:13.468Z",
    "isFallback": false,
    "reason": "Triggered by exceeding 1 PSL absence equivalent (1 PSL, 1 Half-Days, total equivalent: 1.5 days)",
    "tier": 3,
    "updatedAt": "2026-06-04T11:20:28.791Z"
  },
  {
    "_id": "6a215cf34deac4a7e0284e1c",
    "employeeId": "6a21528f453d791e72eae17b",
    "month": 4,
    "year": 2026,
    "__v": 0,
    "createdAt": "2026-06-04T11:09:39.012Z",
    "isFallback": false,
    "reason": "Perfect Attendance: 0 PSL, 0 Half-Days, 0 LWP",
    "tier": 1,
    "updatedAt": "2026-06-05T05:46:34.477Z"
  },
  {
    "_id": "6a1feb68f931bcff1af5caba",
    "employeeId": "6a1d1e3371523c75c540fb5d",
    "year": 2026,
    "month": 4,
    "__v": 0,
    "createdAt": "2026-06-03T08:52:56.062Z",
    "isFallback": false,
    "reason": "Satisfactory Attendance within 1 PSL equivalent: 0 PSL, 2 Half-Days (total equivalent: 1 days)",
    "tier": 2,
    "updatedAt": "2026-06-04T11:19:09.998Z"
  },
  {
    "_id": "6a20ffa14deac4a7e028484c",
    "month": 5,
    "year": 2026,
    "employeeId": "6a201cc9779aee60f9a25fc1",
    "__v": 0,
    "createdAt": "2026-06-04T04:31:29.745Z",
    "isFallback": false,
    "reason": "Satisfactory Attendance within 1 PSL equivalent: 1 PSL, 0 Half-Days (total equivalent: 1 days)",
    "tier": 2,
    "updatedAt": "2026-06-13T06:43:33.788Z"
  },
  {
    "_id": "6a2106ee4deac4a7e02848ec",
    "employeeId": "6a21067d9e4df9a820c22e3d",
    "month": 5,
    "year": 2026,
    "__v": 0,
    "createdAt": "2026-06-04T05:02:38.896Z",
    "isFallback": false,
    "reason": "Triggered by Leave Without Pay (1 LWP days)",
    "tier": 3,
    "updatedAt": "2026-06-13T06:43:37.052Z"
  },
  {
    "_id": "6a2121a14deac4a7e0284af7",
    "employeeId": "6a210aaf9e4df9a820c2308b",
    "month": 5,
    "year": 2026,
    "__v": 0,
    "createdAt": "2026-06-04T06:56:33.408Z",
    "isFallback": false,
    "reason": "Satisfactory Attendance within 1 PSL equivalent: 0 PSL, 2 Half-Days (total equivalent: 1 days)",
    "tier": 2,
    "updatedAt": "2026-06-13T06:43:37.916Z"
  },
  {
    "_id": "6a2121b94deac4a7e0284b37",
    "employeeId": "6a201b0d779aee60f9a25cc7",
    "year": 2026,
    "month": 4,
    "__v": 0,
    "createdAt": "2026-06-04T06:56:57.544Z",
    "isFallback": false,
    "reason": "Triggered by exceeding 1 PSL absence equivalent (1 PSL, 5 Half-Days, total equivalent: 3.5 days)",
    "tier": 3,
    "updatedAt": "2026-06-04T11:19:55.530Z"
  },
  {
    "_id": "6a2121ba4deac4a7e0284b3b",
    "employeeId": "6a201bf9779aee60f9a25e42",
    "month": 4,
    "year": 2026,
    "__v": 0,
    "createdAt": "2026-06-04T06:56:58.725Z",
    "isFallback": false,
    "reason": "Triggered by Leave Without Pay (1 LWP days)",
    "tier": 3,
    "updatedAt": "2026-06-04T11:19:58.363Z"
  },
  {
    "_id": "6a2121bd4deac4a7e0284b45",
    "month": 4,
    "year": 2026,
    "employeeId": "6a201cf5b1c4018e586279cc",
    "__v": 0,
    "createdAt": "2026-06-04T06:57:01.750Z",
    "isFallback": false,
    "reason": "Triggered by Leave Without Pay (1 LWP days)",
    "tier": 3,
    "updatedAt": "2026-06-04T11:20:05.040Z"
  },
  {
    "_id": "6a2121c44deac4a7e0284b5b",
    "employeeId": "6a21067d9e4df9a820c22e3d",
    "month": 4,
    "year": 2026,
    "__v": 0,
    "createdAt": "2026-06-04T06:57:08.130Z",
    "isFallback": false,
    "reason": "Triggered by Leave Without Pay (3 LWP days)",
    "tier": 3,
    "updatedAt": "2026-06-04T11:20:18.277Z"
  },
  {
    "_id": "6a21218e4deac4a7e0284abd",
    "month": 5,
    "employeeId": "6a1ff77b9f42d83bb763779e",
    "year": 2026,
    "__v": 0,
    "createdAt": "2026-06-04T06:56:14.340Z",
    "isFallback": false,
    "reason": "Perfect Attendance: 0 PSL, 0 Half-Days, 0 LWP",
    "tier": 1,
    "updatedAt": "2026-06-13T06:43:27.852Z"
  },
  {
    "_id": "6a21219d4deac4a7e0284aeb",
    "employeeId": "6a201ec19e4df9a820c225b1",
    "year": 2026,
    "month": 5,
    "__v": 0,
    "createdAt": "2026-06-04T06:56:29.493Z",
    "isFallback": false,
    "reason": "Perfect Attendance: 0 PSL, 0 Half-Days, 0 LWP",
    "tier": 1,
    "updatedAt": "2026-06-13T06:43:35.923Z"
  },
  {
    "_id": "6a21219e4deac4a7e0284aed",
    "employeeId": "6a201edd9e4df9a820c225fb",
    "month": 5,
    "year": 2026,
    "__v": 0,
    "createdAt": "2026-06-04T06:56:30.113Z",
    "isFallback": false,
    "reason": "Perfect Attendance: 0 PSL, 0 Half-Days, 0 LWP",
    "tier": 1,
    "updatedAt": "2026-06-13T06:43:36.201Z"
  },
  {
    "_id": "6a2121bb4deac4a7e0284b3d",
    "month": 4,
    "employeeId": "6a201c16779aee60f9a25eca",
    "year": 2026,
    "__v": 0,
    "createdAt": "2026-06-04T06:56:59.233Z",
    "isFallback": false,
    "reason": "Perfect Attendance: 0 PSL, 0 Half-Days, 0 LWP",
    "tier": 1,
    "updatedAt": "2026-06-04T11:19:59.520Z"
  },
  {
    "_id": "6a2121c04deac4a7e0284b4f",
    "employeeId": "6a201e289e4df9a820c22540",
    "year": 2026,
    "month": 4,
    "__v": 0,
    "createdAt": "2026-06-04T06:57:04.438Z",
    "isFallback": false,
    "reason": "Triggered by exceeding 1 PSL absence equivalent (1 PSL, 1 Half-Days, total equivalent: 1.5 days)",
    "tier": 3,
    "updatedAt": "2026-06-04T11:20:11.272Z"
  },
  {
    "_id": "6a2121cf4deac4a7e0284b81",
    "month": 4,
    "employeeId": "6a2119599e4df9a820c23377",
    "year": 2026,
    "__v": 0,
    "createdAt": "2026-06-04T06:57:19.258Z",
    "isFallback": false,
    "reason": "Perfect Attendance: 0 PSL, 0 Half-Days, 0 LWP",
    "tier": 1,
    "updatedAt": "2026-06-04T11:20:40.810Z"
  },
  {
    "_id": "6a1fd024f931bcff1af5c65a",
    "employeeId": "6a1d1e3171523c75c540fb45",
    "month": 4,
    "year": 2026,
    "__v": 0,
    "createdAt": "2026-06-03T06:56:36.691Z",
    "isFallback": false,
    "reason": "Perfect Attendance: 0 PSL, 0 Half-Days, 0 LWP",
    "tier": 1,
    "updatedAt": "2026-06-03T06:56:36.691Z"
  },
  {
    "_id": "6a2121924deac4a7e0284acb",
    "month": 5,
    "year": 2026,
    "employeeId": "6a200a57311c45376c8e6bf4",
    "__v": 0,
    "createdAt": "2026-06-04T06:56:18.423Z",
    "isFallback": false,
    "reason": "Perfect Attendance: 0 PSL, 0 Half-Days, 0 LWP",
    "tier": 1,
    "updatedAt": "2026-06-13T06:43:29.827Z"
  },
  {
    "_id": "6a2121954deac4a7e0284ad3",
    "employeeId": "6a2016e9779aee60f9a25c08",
    "month": 5,
    "year": 2026,
    "__v": 0,
    "createdAt": "2026-06-04T06:56:21.181Z",
    "isFallback": false,
    "reason": "Perfect Attendance: 0 PSL, 0 Half-Days, 0 LWP",
    "tier": 1,
    "updatedAt": "2026-06-13T06:43:31.246Z"
  },
  {
    "_id": "6a21219b4deac4a7e0284ae3",
    "employeeId": "6a201d92b1c4018e58627a34",
    "month": 5,
    "year": 2026,
    "__v": 0,
    "createdAt": "2026-06-04T06:56:27.242Z",
    "isFallback": false,
    "reason": "Satisfactory Attendance within 1 PSL equivalent: 1 PSL, 0 Half-Days (total equivalent: 1 days)",
    "tier": 2,
    "updatedAt": "2026-06-13T06:43:34.610Z"
  },
  {
    "_id": "6a2121b04deac4a7e0284b1b",
    "month": 4,
    "employeeId": "6a2004ae311c45376c8e6b6f",
    "year": 2026,
    "__v": 0,
    "createdAt": "2026-06-04T06:56:48.738Z",
    "isFallback": false,
    "reason": "Triggered by Leave Without Pay (6 LWP days)",
    "tier": 3,
    "updatedAt": "2026-06-04T11:19:32.799Z"
  },
  {
    "_id": "6a2121b14deac4a7e0284b1f",
    "month": 4,
    "employeeId": "6a2007ca311c45376c8e6bd0",
    "year": 2026,
    "__v": 0,
    "createdAt": "2026-06-04T06:56:49.847Z",
    "isFallback": false,
    "reason": "Perfect Attendance: 0 PSL, 0 Half-Days, 0 LWP",
    "tier": 1,
    "updatedAt": "2026-06-04T11:19:37.142Z"
  },
  {
    "_id": "6a2121b54deac4a7e0284b29",
    "employeeId": "6a2013b8943b2ce58f2ba723",
    "year": 2026,
    "month": 4,
    "__v": 0,
    "createdAt": "2026-06-04T06:56:53.259Z",
    "isFallback": false,
    "reason": "Triggered by Leave Without Pay (1 LWP days)",
    "tier": 3,
    "updatedAt": "2026-06-05T05:42:52.147Z"
  },
  {
    "_id": "6a2121be4deac4a7e0284b47",
    "employeeId": "6a201d8fb1c4018e58627a12",
    "month": 4,
    "year": 2026,
    "__v": 0,
    "createdAt": "2026-06-04T06:57:02.249Z",
    "isFallback": false,
    "reason": "Triggered by Leave Without Pay (5 LWP days)",
    "tier": 3,
    "updatedAt": "2026-06-04T11:20:06.447Z"
  },
  {
    "_id": "6a2121c84deac4a7e0284b69",
    "employeeId": "6a210bcf9e4df9a820c230f2",
    "year": 2026,
    "month": 4,
    "__v": 0,
    "createdAt": "2026-06-04T06:57:12.253Z",
    "isFallback": false,
    "reason": "Triggered by Leave Without Pay (6 LWP days)",
    "tier": 3,
    "updatedAt": "2026-06-04T11:20:26.322Z"
  },
  {
    "_id": "6a2121ca4deac4a7e0284b6f",
    "month": 4,
    "year": 2026,
    "employeeId": "6a210c699e4df9a820c23111",
    "__v": 0,
    "createdAt": "2026-06-04T06:57:14.030Z",
    "isFallback": false,
    "reason": "Perfect Attendance: 0 PSL, 0 Half-Days, 0 LWP",
    "tier": 1,
    "updatedAt": "2026-06-04T11:20:29.984Z"
  },
  {
    "_id": "6a1feb3af931bcff1af5ca8c",
    "month": 5,
    "employeeId": "6a1d1e3171523c75c540fb49",
    "year": 2026,
    "__v": 0,
    "createdAt": "2026-06-03T08:52:10.254Z",
    "isFallback": false,
    "reason": "Satisfactory Attendance within 1 PSL equivalent: 1 PSL, 0 Half-Days (total equivalent: 1 days)",
    "tier": 2,
    "updatedAt": "2026-06-13T06:43:24.754Z"
  },
  {
    "_id": "6a1feb69f931bcff1af5cac4",
    "month": 4,
    "employeeId": "6a1fe9189f42d83bb7636c58",
    "year": 2026,
    "__v": 0,
    "createdAt": "2026-06-03T08:52:57.364Z",
    "isFallback": false,
    "reason": "Perfect Attendance: 0 PSL, 0 Half-Days, 0 LWP",
    "tier": 1,
    "updatedAt": "2026-06-04T11:19:26.932Z"
  },
  {
    "_id": "6a20ffaf4deac4a7e0284850",
    "employeeId": "6a201d8fb1c4018e58627a12",
    "month": 5,
    "year": 2026,
    "__v": 0,
    "createdAt": "2026-06-04T04:31:43.692Z",
    "isFallback": false,
    "reason": "Satisfactory Attendance within 1 PSL equivalent: 0 PSL, 1 Half-Days (total equivalent: 0.5 days)",
    "tier": 2,
    "updatedAt": "2026-06-13T06:43:34.336Z"
  },
  {
    "_id": "6a21218f4deac4a7e0284abf",
    "month": 5,
    "year": 2026,
    "employeeId": "6a2004ae311c45376c8e6b6f",
    "__v": 0,
    "createdAt": "2026-06-04T06:56:14.891Z",
    "isFallback": false,
    "reason": "Perfect Attendance: 0 PSL, 0 Half-Days, 0 LWP",
    "tier": 1,
    "updatedAt": "2026-06-13T06:43:28.128Z"
  },
  {
    "_id": "6a2121994deac4a7e0284add",
    "month": 5,
    "year": 2026,
    "employeeId": "6a201c16779aee60f9a25eca",
    "__v": 0,
    "createdAt": "2026-06-04T06:56:24.918Z",
    "isFallback": false,
    "reason": "Perfect Attendance: 0 PSL, 0 Half-Days, 0 LWP",
    "tier": 1,
    "updatedAt": "2026-06-13T06:43:32.901Z"
  },
  {
    "_id": "6a21219f4deac4a7e0284af1",
    "employeeId": "6a20584d9e4df9a820c22ab5",
    "month": 5,
    "year": 2026,
    "__v": 0,
    "createdAt": "2026-06-04T06:56:31.391Z",
    "isFallback": false,
    "reason": "Perfect Attendance: 0 PSL, 0 Half-Days, 0 LWP",
    "tier": 1,
    "updatedAt": "2026-06-13T06:43:36.767Z"
  },
  {
    "_id": "6a2121a04deac4a7e0284af5",
    "month": 5,
    "employeeId": "6a21089b9e4df9a820c22f0f",
    "year": 2026,
    "__v": 0,
    "createdAt": "2026-06-04T06:56:32.603Z",
    "isFallback": false,
    "reason": "Satisfactory Attendance within 1 PSL equivalent: 0 PSL, 1 Half-Days (total equivalent: 0.5 days)",
    "tier": 2,
    "updatedAt": "2026-06-13T06:43:37.616Z"
  },
  {
    "_id": "6a2121b74deac4a7e0284b2f",
    "month": 4,
    "year": 2026,
    "employeeId": "6a20168d779aee60f9a25b9e",
    "__v": 0,
    "createdAt": "2026-06-04T06:56:55.376Z",
    "isFallback": false,
    "reason": "Perfect Attendance: 0 PSL, 0 Half-Days, 0 LWP",
    "tier": 1,
    "updatedAt": "2026-06-04T11:19:50.126Z"
  },
  {
    "_id": "6a2121ca4deac4a7e0284b71",
    "employeeId": "6a210c869e4df9a820c2311a",
    "year": 2026,
    "month": 4,
    "__v": 0,
    "createdAt": "2026-06-04T06:57:14.543Z",
    "isFallback": false,
    "reason": "Triggered by exceeding 1 PSL absence equivalent (1 PSL, 1 Half-Days, total equivalent: 1.5 days)",
    "tier": 3,
    "updatedAt": "2026-06-04T11:20:31.178Z"
  },
  {
    "_id": "6a1feb38f931bcff1af5ca81",
    "month": 5,
    "year": 2026,
    "employeeId": "6a1d1e2f71523c75c540fb35",
    "__v": 0,
    "createdAt": "2026-06-03T08:52:08.796Z",
    "isFallback": false,
    "reason": "Satisfactory Attendance within 1 PSL equivalent: 1 PSL, 0 Half-Days (total equivalent: 1 days)",
    "tier": 2,
    "updatedAt": "2026-06-13T06:43:23.631Z"
  },
  {
    "_id": "6a1feb68f931bcff1af5cabe",
    "month": 4,
    "employeeId": "6a1fcb409f42d83bb7635f57",
    "year": 2026,
    "__v": 0,
    "createdAt": "2026-06-03T08:52:56.565Z",
    "isFallback": false,
    "reason": "Triggered by exceeding 1 PSL absence equivalent (1 PSL, 2 Half-Days, total equivalent: 2 days)",
    "tier": 3,
    "updatedAt": "2026-06-04T11:19:15.925Z"
  },
  {
    "_id": "6a2121914deac4a7e0284ac9",
    "employeeId": "6a200920311c45376c8e6beb",
    "month": 5,
    "year": 2026,
    "__v": 0,
    "createdAt": "2026-06-04T06:56:17.856Z",
    "isFallback": false,
    "reason": "Perfect Attendance: 0 PSL, 0 Half-Days, 0 LWP",
    "tier": 1,
    "updatedAt": "2026-06-13T06:43:29.545Z"
  },
  {
    "_id": "6a2121934deac4a7e0284acf",
    "employeeId": "6a2015e0779aee60f9a25b95",
    "year": 2026,
    "month": 5,
    "__v": 0,
    "createdAt": "2026-06-04T06:56:19.664Z",
    "isFallback": false,
    "reason": "Perfect Attendance: 0 PSL, 0 Half-Days, 0 LWP",
    "tier": 1,
    "updatedAt": "2026-06-13T06:43:30.682Z"
  },
  {
    "_id": "6a2121a54deac4a7e0284b01",
    "employeeId": "6a210be39e4df9a820c230fb",
    "year": 2026,
    "month": 5,
    "__v": 0,
    "createdAt": "2026-06-04T06:56:36.906Z",
    "isFallback": false,
    "reason": "Perfect Attendance: 0 PSL, 0 Half-Days, 0 LWP",
    "tier": 1,
    "updatedAt": "2026-06-13T06:43:39.352Z"
  },
  {
    "_id": "6a2121a54deac4a7e0284b03",
    "employeeId": "6a210c199e4df9a820c23108",
    "year": 2026,
    "month": 5,
    "__v": 0,
    "createdAt": "2026-06-04T06:56:37.529Z",
    "isFallback": false,
    "reason": "Triggered by Leave Without Pay (2 LWP days)",
    "tier": 3,
    "updatedAt": "2026-06-13T06:43:39.635Z"
  },
  {
    "_id": "6a2121a84deac4a7e0284b0d",
    "employeeId": "6a210d579e4df9a820c231c3",
    "year": 2026,
    "month": 5,
    "__v": 0,
    "createdAt": "2026-06-04T06:56:40.650Z",
    "isFallback": false,
    "reason": "Triggered by Leave Without Pay (1 LWP days)",
    "tier": 3,
    "updatedAt": "2026-06-13T06:43:41.068Z"
  },
  {
    "_id": "6a2121ba4deac4a7e0284b39",
    "employeeId": "6a201bf1779aee60f9a25db2",
    "year": 2026,
    "month": 4,
    "__v": 0,
    "createdAt": "2026-06-04T06:56:58.114Z",
    "isFallback": false,
    "reason": "Satisfactory Attendance within 1 PSL equivalent: 0 PSL, 1 Half-Days (total equivalent: 0.5 days)",
    "tier": 2,
    "updatedAt": "2026-06-04T11:19:57.044Z"
  },
  {
    "_id": "6a1fe92ff931bcff1af5ca6e",
    "month": 5,
    "year": 2026,
    "employeeId": "6a1fe9189f42d83bb7636c58",
    "__v": 0,
    "createdAt": "2026-06-03T08:43:27.643Z",
    "isFallback": false,
    "reason": "Perfect Attendance: 0 PSL, 0 Half-Days, 0 LWP",
    "tier": 1,
    "updatedAt": "2026-06-13T06:43:27.574Z"
  },
  {
    "_id": "6a1feb69f931bcff1af5cac0",
    "employeeId": "6a1fcba29f42d83bb7635f86",
    "month": 4,
    "year": 2026,
    "__v": 0,
    "createdAt": "2026-06-03T08:52:56.836Z",
    "isFallback": false,
    "reason": "Satisfactory Attendance within 1 PSL equivalent: 0 PSL, 1 Half-Days (total equivalent: 0.5 days)",
    "tier": 2,
    "updatedAt": "2026-06-05T05:03:49.718Z"
  },
  {
    "_id": "6a1feb69f931bcff1af5cac2",
    "month": 4,
    "employeeId": "6a1fd4ce9f42d83bb763668c",
    "year": 2026,
    "__v": 0,
    "createdAt": "2026-06-03T08:52:57.097Z",
    "isFallback": false,
    "reason": "Satisfactory Attendance within 1 PSL equivalent: 1 PSL, 0 Half-Days (total equivalent: 1 days)",
    "tier": 2,
    "updatedAt": "2026-06-05T04:44:29.950Z"
  },
  {
    "_id": "6a20fff34deac4a7e028485b",
    "employeeId": "6a201bf1779aee60f9a25db2",
    "year": 2026,
    "month": 5,
    "__v": 0,
    "createdAt": "2026-06-04T04:32:51.227Z",
    "isFallback": false,
    "reason": "Perfect Attendance: 0 PSL, 0 Half-Days, 0 LWP",
    "tier": 1,
    "updatedAt": "2026-06-13T06:43:32.339Z"
  },
  {
    "_id": "6a2121904deac4a7e0284ac3",
    "employeeId": "6a2007ca311c45376c8e6bd0",
    "year": 2026,
    "month": 5,
    "__v": 0,
    "createdAt": "2026-06-04T06:56:16.043Z",
    "isFallback": false,
    "reason": "Perfect Attendance: 0 PSL, 0 Half-Days, 0 LWP",
    "tier": 1,
    "updatedAt": "2026-06-13T06:43:28.692Z"
  },
  {
    "_id": "6a2121a04deac4a7e0284af3",
    "month": 5,
    "year": 2026,
    "employeeId": "6a2107b79e4df9a820c22ee8",
    "__v": 0,
    "createdAt": "2026-06-04T06:56:32.077Z",
    "isFallback": false,
    "reason": "Perfect Attendance: 0 PSL, 0 Half-Days, 0 LWP",
    "tier": 1,
    "updatedAt": "2026-06-13T06:43:37.332Z"
  },
  {
    "_id": "6a2121aa4deac4a7e0284b13",
    "month": 5,
    "employeeId": "6a210e119e4df9a820c231ea",
    "year": 2026,
    "__v": 0,
    "createdAt": "2026-06-04T06:56:42.431Z",
    "isFallback": false,
    "reason": "Satisfactory Attendance within 1 PSL equivalent: 1 PSL, 0 Half-Days (total equivalent: 1 days)",
    "tier": 2,
    "updatedAt": "2026-06-13T06:43:41.906Z"
  },
  {
    "_id": "6a2121b34deac4a7e0284b23",
    "employeeId": "6a20089f311c45376c8e6be2",
    "month": 4,
    "year": 2026,
    "__v": 0,
    "createdAt": "2026-06-04T06:56:51.011Z",
    "isFallback": false,
    "reason": "Triggered by Leave Without Pay (1 LWP days)",
    "tier": 3,
    "updatedAt": "2026-06-04T11:19:40.407Z"
  },
  {
    "_id": "6a2121bf4deac4a7e0284b4b",
    "month": 4,
    "year": 2026,
    "employeeId": "6a201e0ab1c4018e58627ab8",
    "__v": 0,
    "createdAt": "2026-06-04T06:57:03.380Z",
    "isFallback": false,
    "reason": "Satisfactory Attendance within 1 PSL equivalent: 1 PSL, 0 Half-Days (total equivalent: 1 days)",
    "tier": 2,
    "updatedAt": "2026-06-04T11:20:08.900Z"
  },
  {
    "_id": "6a2121c54deac4a7e0284b5f",
    "employeeId": "6a21089b9e4df9a820c22f0f",
    "month": 4,
    "year": 2026,
    "__v": 0,
    "createdAt": "2026-06-04T06:57:09.298Z",
    "isFallback": false,
    "reason": "Perfect Attendance: 0 PSL, 0 Half-Days, 0 LWP",
    "tier": 1,
    "updatedAt": "2026-06-04T11:20:20.577Z"
  },
  {
    "_id": "6a2121c74deac4a7e0284b65",
    "month": 4,
    "year": 2026,
    "employeeId": "6a210b329e4df9a820c230c2",
    "__v": 0,
    "createdAt": "2026-06-04T06:57:10.886Z",
    "isFallback": false,
    "reason": "Triggered by exceeding 1 PSL absence equivalent (1 PSL, 1 Half-Days, total equivalent: 1.5 days)",
    "tier": 3,
    "updatedAt": "2026-06-04T11:20:24.040Z"
  },
  {
    "_id": "6a2121ce4deac4a7e0284b7f",
    "month": 4,
    "employeeId": "6a21189d9e4df9a820c23333",
    "year": 2026,
    "__v": 0,
    "createdAt": "2026-06-04T06:57:18.722Z",
    "isFallback": false,
    "reason": "Perfect Attendance: 0 PSL, 0 Half-Days, 0 LWP",
    "tier": 1,
    "updatedAt": "2026-06-04T11:20:39.595Z"
  },
  {
    "_id": "6a224dd54deac4a7e028530c",
    "employeeId": "6a1d1e3071523c75c540fb39",
    "month": 3,
    "year": 2026,
    "__v": 0,
    "createdAt": "2026-06-05T04:17:25.107Z",
    "isFallback": false,
    "reason": "Perfect Attendance: 0 PSL, 0 Half-Days, 0 LWP",
    "tier": 1,
    "updatedAt": "2026-06-05T04:17:35.043Z"
  },
  {
    "_id": "6a22651f4deac4a7e0285391",
    "month": 4,
    "employeeId": "6a2264afe30358b77365b103",
    "year": 2026,
    "__v": 0,
    "createdAt": "2026-06-05T05:56:47.051Z",
    "isFallback": false,
    "reason": "Triggered by exceeding 1 PSL absence equivalent (1 PSL, 2 Half-Days, total equivalent: 2 days)",
    "tier": 3,
    "updatedAt": "2026-06-05T05:59:58.025Z"
  },
  {
    "_id": "6a1feb66f931bcff1af5caae",
    "month": 4,
    "year": 2026,
    "employeeId": "6a1d1e3071523c75c540fb41",
    "__v": 0,
    "createdAt": "2026-06-03T08:52:54.403Z",
    "isFallback": false,
    "reason": "Satisfactory Attendance within 1 PSL equivalent: 1 PSL, 0 Half-Days (total equivalent: 1 days)",
    "tier": 2,
    "updatedAt": "2026-06-04T11:18:52.544Z"
  },
  {
    "_id": "6a1feb67f931bcff1af5cab8",
    "month": 4,
    "employeeId": "6a1d1e3271523c75c540fb59",
    "year": 2026,
    "__v": 0,
    "createdAt": "2026-06-03T08:52:55.794Z",
    "isFallback": false,
    "reason": "Perfect Attendance: 0 PSL, 0 Half-Days, 0 LWP",
    "tier": 1,
    "updatedAt": "2026-06-04T11:19:08.455Z"
  },
  {
    "_id": "6a21219d4deac4a7e0284ae9",
    "employeeId": "6a201e779e4df9a820c225a8",
    "month": 5,
    "year": 2026,
    "__v": 0,
    "createdAt": "2026-06-04T06:56:28.979Z",
    "isFallback": false,
    "reason": "Perfect Attendance: 0 PSL, 0 Half-Days, 0 LWP",
    "tier": 1,
    "updatedAt": "2026-06-13T06:43:35.671Z"
  },
  {
    "_id": "6a2121ab4deac4a7e0284b15",
    "employeeId": "6a21189d9e4df9a820c23333",
    "month": 5,
    "year": 2026,
    "__v": 0,
    "createdAt": "2026-06-04T06:56:43.112Z",
    "isFallback": false,
    "reason": "Perfect Attendance: 0 PSL, 0 Half-Days, 0 LWP",
    "tier": 1,
    "updatedAt": "2026-06-13T06:43:42.188Z"
  },
  {
    "_id": "6a2121b34deac4a7e0284b25",
    "month": 4,
    "employeeId": "6a200920311c45376c8e6beb",
    "year": 2026,
    "__v": 0,
    "createdAt": "2026-06-04T06:56:51.862Z",
    "isFallback": false,
    "reason": "Perfect Attendance: 0 PSL, 0 Half-Days, 0 LWP",
    "tier": 1,
    "updatedAt": "2026-06-04T11:19:42.128Z"
  },
  {
    "_id": "6a2121c74deac4a7e0284b67",
    "employeeId": "6a210b709e4df9a820c230cb",
    "year": 2026,
    "month": 4,
    "__v": 0,
    "createdAt": "2026-06-04T06:57:11.449Z",
    "isFallback": false,
    "reason": "Satisfactory Attendance within 1 PSL equivalent: 0 PSL, 2 Half-Days (total equivalent: 1 days)",
    "tier": 2,
    "updatedAt": "2026-06-04T11:20:25.199Z"
  },
  {
    "_id": "6a2121c84deac4a7e0284b6b",
    "month": 4,
    "employeeId": "6a210be39e4df9a820c230fb",
    "year": 2026,
    "__v": 0,
    "createdAt": "2026-06-04T06:57:12.786Z",
    "isFallback": false,
    "reason": "Satisfactory Attendance within 1 PSL equivalent: 0 PSL, 1 Half-Days (total equivalent: 0.5 days)",
    "tier": 2,
    "updatedAt": "2026-06-04T11:20:27.591Z"
  },
  {
    "_id": "6a2121cb4deac4a7e0284b75",
    "month": 4,
    "employeeId": "6a210d159e4df9a820c2319c",
    "year": 2026,
    "__v": 0,
    "createdAt": "2026-06-04T06:57:15.751Z",
    "isFallback": false,
    "reason": "Triggered by exceeding 1 PSL absence equivalent (1 PSL, 1 Half-Days, total equivalent: 1.5 days)",
    "tier": 3,
    "updatedAt": "2026-06-04T11:20:33.530Z"
  },
  {
    "_id": "6a1fd1dff931bcff1af5c6f3",
    "employeeId": "6a1d1e3171523c75c540fb45",
    "year": 2027,
    "month": 5,
    "__v": 0,
    "createdAt": "2026-06-03T07:03:59.620Z",
    "isFallback": false,
    "reason": "Perfect Attendance: 0 PSL, 0 Half-Days, 0 LWP",
    "tier": 1,
    "updatedAt": "2026-06-03T07:03:59.620Z"
  },
  {
    "_id": "6a1feb39f931bcff1af5ca83",
    "month": 5,
    "year": 2026,
    "employeeId": "6a1d1e3071523c75c540fb39",
    "__v": 0,
    "createdAt": "2026-06-03T08:52:09.125Z",
    "isFallback": false,
    "reason": "Perfect Attendance: 0 PSL, 0 Half-Days, 0 LWP",
    "tier": 1,
    "updatedAt": "2026-06-13T06:43:23.917Z"
  },
  {
    "_id": "6a1feb3af931bcff1af5ca8f",
    "month": 5,
    "employeeId": "6a1d1e3171523c75c540fb4d",
    "year": 2026,
    "__v": 0,
    "createdAt": "2026-06-03T08:52:10.640Z",
    "isFallback": false,
    "reason": "Perfect Attendance: 0 PSL, 0 Half-Days, 0 LWP",
    "tier": 1,
    "updatedAt": "2026-06-13T06:43:25.033Z"
  },
  {
    "_id": "6a1feb66f931bcff1af5caac",
    "employeeId": "6a1d1e3071523c75c540fb3d",
    "month": 4,
    "year": 2026,
    "__v": 0,
    "createdAt": "2026-06-03T08:52:54.160Z",
    "isFallback": false,
    "reason": "Perfect Attendance: 0 PSL, 0 Half-Days, 0 LWP",
    "tier": 1,
    "updatedAt": "2026-06-04T11:18:49.910Z"
  },
  {
    "_id": "6a1feb67f931bcff1af5cab4",
    "employeeId": "6a1d1e3271523c75c540fb51",
    "year": 2026,
    "month": 4,
    "__v": 0,
    "createdAt": "2026-06-03T08:52:55.240Z",
    "isFallback": false,
    "reason": "Satisfactory Attendance within 1 PSL equivalent: 1 PSL, 0 Half-Days (total equivalent: 1 days)",
    "tier": 2,
    "updatedAt": "2026-06-04T11:19:03.680Z"
  },
  {
    "_id": "6a21219a4deac4a7e0284ae1",
    "employeeId": "6a201cf5b1c4018e586279cc",
    "year": 2026,
    "month": 5,
    "__v": 0,
    "createdAt": "2026-06-04T06:56:26.594Z",
    "isFallback": false,
    "reason": "Perfect Attendance: 0 PSL, 0 Half-Days, 0 LWP",
    "tier": 1,
    "updatedAt": "2026-06-13T06:43:34.069Z"
  },
  {
    "_id": "6a2121a44deac4a7e0284aff",
    "employeeId": "6a210bcf9e4df9a820c230f2",
    "year": 2026,
    "month": 5,
    "__v": 0,
    "createdAt": "2026-06-04T06:56:36.310Z",
    "isFallback": false,
    "reason": "Perfect Attendance: 0 PSL, 0 Half-Days, 0 LWP",
    "tier": 1,
    "updatedAt": "2026-06-13T06:43:39.068Z"
  },
  {
    "_id": "6a2121b84deac4a7e0284b33",
    "month": 4,
    "year": 2026,
    "employeeId": "6a2017ee779aee60f9a25c11",
    "__v": 0,
    "createdAt": "2026-06-04T06:56:56.485Z",
    "isFallback": false,
    "reason": "Perfect Attendance: 0 PSL, 0 Half-Days, 0 LWP",
    "tier": 1,
    "updatedAt": "2026-06-04T11:19:52.529Z"
  },
  {
    "_id": "6a2121c14deac4a7e0284b53",
    "employeeId": "6a201ec19e4df9a820c225b1",
    "year": 2026,
    "month": 4,
    "__v": 0,
    "createdAt": "2026-06-04T06:57:05.542Z",
    "isFallback": false,
    "reason": "Satisfactory Attendance within 1 PSL equivalent: 1 PSL, 0 Half-Days (total equivalent: 1 days)",
    "tier": 2,
    "updatedAt": "2026-06-04T11:20:13.642Z"
  },
  {
    "_id": "6a2121c24deac4a7e0284b55",
    "employeeId": "6a201edd9e4df9a820c225fb",
    "year": 2026,
    "month": 4,
    "__v": 0,
    "createdAt": "2026-06-04T06:57:06.097Z",
    "isFallback": false,
    "reason": "Perfect Attendance: 0 PSL, 0 Half-Days, 0 LWP",
    "tier": 1,
    "updatedAt": "2026-06-04T11:20:14.782Z"
  },
  {
    "_id": "6a2121cd4deac4a7e0284b79",
    "month": 4,
    "employeeId": "6a210d5a9e4df9a820c231cc",
    "year": 2026,
    "__v": 0,
    "createdAt": "2026-06-04T06:57:16.952Z",
    "isFallback": false,
    "reason": "Triggered by Leave Without Pay (1 LWP days)",
    "tier": 3,
    "updatedAt": "2026-06-04T11:20:35.990Z"
  },
  {
    "_id": "6a1feb67f931bcff1af5cab6",
    "month": 4,
    "employeeId": "6a1d1e3271523c75c540fb55",
    "year": 2026,
    "__v": 0,
    "createdAt": "2026-06-03T08:52:55.490Z",
    "isFallback": false,
    "reason": "Perfect Attendance: 0 PSL, 0 Half-Days, 0 LWP",
    "tier": 1,
    "updatedAt": "2026-06-04T11:19:06.141Z"
  },
  {
    "_id": "6a21219c4deac4a7e0284ae5",
    "employeeId": "6a201e0ab1c4018e58627ab8",
    "year": 2026,
    "month": 5,
    "__v": 0,
    "createdAt": "2026-06-04T06:56:27.980Z",
    "isFallback": false,
    "reason": "Perfect Attendance: 0 PSL, 0 Half-Days, 0 LWP",
    "tier": 1,
    "updatedAt": "2026-06-13T06:43:34.884Z"
  },
  {
    "_id": "6a2121a84deac4a7e0284b0b",
    "month": 5,
    "year": 2026,
    "employeeId": "6a210d159e4df9a820c2319c",
    "__v": 0,
    "createdAt": "2026-06-04T06:56:40.079Z",
    "isFallback": false,
    "reason": "Perfect Attendance: 0 PSL, 0 Half-Days, 0 LWP",
    "tier": 1,
    "updatedAt": "2026-06-13T06:43:40.787Z"
  },
  {
    "_id": "6a2121b04deac4a7e0284b19",
    "employeeId": "6a1ff77b9f42d83bb763779e",
    "month": 4,
    "year": 2026,
    "__v": 0,
    "createdAt": "2026-06-04T06:56:48.146Z",
    "isFallback": false,
    "reason": "Satisfactory Attendance within 1 PSL equivalent: 0 PSL, 1 Half-Days (total equivalent: 0.5 days)",
    "tier": 2,
    "updatedAt": "2026-06-04T11:19:29.458Z"
  },
  {
    "_id": "6a2121b14deac4a7e0284b1d",
    "employeeId": "6a20052a311c45376c8e6b78",
    "year": 2026,
    "month": 4,
    "__v": 0,
    "createdAt": "2026-06-04T06:56:49.265Z",
    "isFallback": false,
    "reason": "Satisfactory Attendance within 1 PSL equivalent: 1 PSL, 0 Half-Days (total equivalent: 1 days)",
    "tier": 2,
    "updatedAt": "2026-06-04T11:19:35.085Z"
  },
  {
    "_id": "6a2121be4deac4a7e0284b49",
    "employeeId": "6a201d92b1c4018e58627a34",
    "year": 2026,
    "month": 4,
    "__v": 0,
    "createdAt": "2026-06-04T06:57:02.861Z",
    "isFallback": false,
    "reason": "Perfect Attendance: 0 PSL, 0 Half-Days, 0 LWP",
    "tier": 1,
    "updatedAt": "2026-06-04T11:20:07.666Z"
  },
  {
    "_id": "6a2121c54deac4a7e0284b61",
    "month": 4,
    "employeeId": "6a210aaf9e4df9a820c2308b",
    "year": 2026,
    "__v": 0,
    "createdAt": "2026-06-04T06:57:09.849Z",
    "isFallback": false,
    "reason": "Triggered by Leave Without Pay (2 LWP days)",
    "tier": 3,
    "updatedAt": "2026-06-04T11:20:21.704Z"
  },
  {
    "_id": "6a2121ce4deac4a7e0284b7d",
    "employeeId": "6a210e119e4df9a820c231ea",
    "year": 2026,
    "month": 4,
    "__v": 0,
    "createdAt": "2026-06-04T06:57:18.179Z",
    "isFallback": false,
    "reason": "Perfect Attendance: 0 PSL, 0 Half-Days, 0 LWP",
    "tier": 1,
    "updatedAt": "2026-06-04T11:20:38.443Z"
  },
  {
    "_id": "6a22ae48be24f7143c648685",
    "year": 2026,
    "month": 5,
    "employeeId": "6a21640a1d3fe393896fe5cc",
    "__v": 0,
    "createdAt": "2026-06-05T11:08:55.994Z",
    "isFallback": false,
    "reason": "Perfect Attendance: 0 PSL, 0 Half-Days, 0 LWP",
    "tier": 1,
    "updatedAt": "2026-06-13T06:43:43.406Z"
  },
  {
    "_id": "6a22ae48be24f7143c648687",
    "employeeId": "6a226501e30358b77365b1d8",
    "month": 5,
    "year": 2026,
    "__v": 0,
    "createdAt": "2026-06-05T11:08:56.593Z",
    "isFallback": false,
    "reason": "Perfect Attendance: 0 PSL, 0 Half-Days, 0 LWP",
    "tier": 1,
    "updatedAt": "2026-06-13T06:43:44.244Z"
  },
  {
    "_id": "6a22ae49be24f7143c648689",
    "year": 2026,
    "employeeId": "6a226554e30358b77365b48b",
    "month": 5,
    "__v": 0,
    "createdAt": "2026-06-05T11:08:57.520Z",
    "isFallback": false,
    "reason": "Triggered by Leave Without Pay (1 LWP days)",
    "tier": 3,
    "updatedAt": "2026-06-13T06:43:44.519Z"
  },
  {
    "_id": "6a22ae9abe24f7143c64868b",
    "year": 2026,
    "month": 4,
    "employeeId": "6a21640a1d3fe393896fe5cc",
    "__v": 0,
    "createdAt": "2026-06-05T11:10:18.379Z",
    "isFallback": false,
    "reason": "Perfect Attendance: 0 PSL, 0 Half-Days, 0 LWP",
    "tier": 1,
    "updatedAt": "2026-06-05T11:10:18.379Z"
  },
  {
    "_id": "6a22ae9bbe24f7143c64868d",
    "year": 2026,
    "employeeId": "6a2164791d3fe393896fe5e9",
    "month": 4,
    "__v": 0,
    "createdAt": "2026-06-05T11:10:19.136Z",
    "isFallback": false,
    "reason": "Perfect Attendance: 0 PSL, 0 Half-Days, 0 LWP",
    "tier": 1,
    "updatedAt": "2026-06-05T11:10:19.136Z"
  },
  {
    "_id": "6a22ae9cbe24f7143c64868f",
    "year": 2026,
    "month": 4,
    "employeeId": "6a226501e30358b77365b1d8",
    "__v": 0,
    "createdAt": "2026-06-05T11:10:19.734Z",
    "isFallback": false,
    "reason": "Triggered by Leave Without Pay (2 LWP days)",
    "tier": 3,
    "updatedAt": "2026-06-05T11:10:19.734Z"
  },
  {
    "_id": "6a22ae9cbe24f7143c648691",
    "employeeId": "6a226554e30358b77365b48b",
    "month": 4,
    "year": 2026,
    "__v": 0,
    "createdAt": "2026-06-05T11:10:20.409Z",
    "isFallback": false,
    "reason": "Triggered by Leave Without Pay (3 LWP days)",
    "tier": 3,
    "updatedAt": "2026-06-05T11:10:20.409Z"
  },
  {
    "_id": "6a5df1f47a6effd18ee40850",
    "employeeId": "6a201d92b1c4018e58627a34",
    "year": 2026,
    "month": 6,
    "__v": 0,
    "createdAt": "2026-07-20T10:01:24.628Z",
    "isFallback": false,
    "reason": "Perfect Attendance: 0 PSL, 0 Half-Days, 0 LWP",
    "tier": 1,
    "updatedAt": "2026-07-20T10:01:24.628Z"
  },
  {
    "_id": "6a5df1f57a6effd18ee40852",
    "month": 6,
    "year": 2026,
    "employeeId": "6a210be39e4df9a820c230fb",
    "__v": 0,
    "createdAt": "2026-07-20T10:01:25.469Z",
    "isFallback": false,
    "reason": "Perfect Attendance: 0 PSL, 0 Half-Days, 0 LWP",
    "tier": 1,
    "updatedAt": "2026-07-20T10:01:25.469Z"
  },
  {
    "_id": "6a5df1f57a6effd18ee40854",
    "month": 6,
    "employeeId": "6a201e779e4df9a820c225a8",
    "year": 2026,
    "__v": 0,
    "createdAt": "2026-07-20T10:01:25.976Z",
    "isFallback": false,
    "reason": "Perfect Attendance: 0 PSL, 0 Half-Days, 0 LWP",
    "tier": 1,
    "updatedAt": "2026-07-20T10:01:25.976Z"
  },
  {
    "_id": "6a5df1f67a6effd18ee40856",
    "employeeId": "6a210b1e9e4df9a820c230b9",
    "year": 2026,
    "month": 6,
    "__v": 0,
    "createdAt": "2026-07-20T10:01:26.404Z",
    "isFallback": false,
    "reason": "Perfect Attendance: 0 PSL, 0 Half-Days, 0 LWP",
    "tier": 1,
    "updatedAt": "2026-07-20T10:01:26.404Z"
  },
  {
    "_id": "6a5df1f67a6effd18ee40858",
    "employeeId": "6a210b709e4df9a820c230cb",
    "month": 6,
    "year": 2026,
    "__v": 0,
    "createdAt": "2026-07-20T10:01:26.912Z",
    "isFallback": false,
    "reason": "Perfect Attendance: 0 PSL, 0 Half-Days, 0 LWP",
    "tier": 1,
    "updatedAt": "2026-07-20T10:01:26.912Z"
  },
  {
    "_id": "6a5df1f77a6effd18ee4085a",
    "month": 6,
    "employeeId": "6a210c869e4df9a820c2311a",
    "year": 2026,
    "__v": 0,
    "createdAt": "2026-07-20T10:01:27.329Z",
    "isFallback": false,
    "reason": "Perfect Attendance: 0 PSL, 0 Half-Days, 0 LWP",
    "tier": 1,
    "updatedAt": "2026-07-20T10:01:27.329Z"
  },
  {
    "_id": "6a5df1f77a6effd18ee4085c",
    "employeeId": "6a21189d9e4df9a820c23333",
    "year": 2026,
    "month": 6,
    "__v": 0,
    "createdAt": "2026-07-20T10:01:27.832Z",
    "isFallback": false,
    "reason": "Perfect Attendance: 0 PSL, 0 Half-Days, 0 LWP",
    "tier": 1,
    "updatedAt": "2026-07-20T10:01:27.832Z"
  },
  {
    "_id": "6a5df1f87a6effd18ee4085e",
    "employeeId": "6a1fcba29f42d83bb7635f86",
    "month": 6,
    "year": 2026,
    "__v": 0,
    "createdAt": "2026-07-20T10:01:28.270Z",
    "isFallback": false,
    "reason": "Perfect Attendance: 0 PSL, 0 Half-Days, 0 LWP",
    "tier": 1,
    "updatedAt": "2026-07-20T10:01:28.270Z"
  },
  {
    "_id": "6a5df1f87a6effd18ee40860",
    "employeeId": "6a2016e9779aee60f9a25c08",
    "year": 2026,
    "month": 6,
    "__v": 0,
    "createdAt": "2026-07-20T10:01:28.818Z",
    "isFallback": false,
    "reason": "Perfect Attendance: 0 PSL, 0 Half-Days, 0 LWP",
    "tier": 1,
    "updatedAt": "2026-07-20T10:01:28.818Z"
  },
  {
    "_id": "6a5df1f97a6effd18ee40862",
    "employeeId": "6a210d579e4df9a820c231c3",
    "year": 2026,
    "month": 6,
    "__v": 0,
    "createdAt": "2026-07-20T10:01:29.287Z",
    "isFallback": false,
    "reason": "Perfect Attendance: 0 PSL, 0 Half-Days, 0 LWP",
    "tier": 1,
    "updatedAt": "2026-07-20T10:01:29.287Z"
  },
  {
    "_id": "6a5df1f97a6effd18ee40864",
    "employeeId": "6a210d5a9e4df9a820c231cc",
    "year": 2026,
    "month": 6,
    "__v": 0,
    "createdAt": "2026-07-20T10:01:29.886Z",
    "isFallback": false,
    "reason": "Perfect Attendance: 0 PSL, 0 Half-Days, 0 LWP",
    "tier": 1,
    "updatedAt": "2026-07-20T10:01:29.886Z"
  },
  {
    "_id": "6a5df1fa7a6effd18ee40866",
    "employeeId": "6a1d1e3071523c75c540fb3d",
    "year": 2026,
    "month": 6,
    "__v": 0,
    "createdAt": "2026-07-20T10:01:30.280Z",
    "isFallback": false,
    "reason": "Perfect Attendance: 0 PSL, 0 Half-Days, 0 LWP",
    "tier": 1,
    "updatedAt": "2026-07-20T10:01:30.280Z"
  },
  {
    "_id": "6a5df1fa7a6effd18ee40868",
    "month": 6,
    "employeeId": "6a1fe9189f42d83bb7636c58",
    "year": 2026,
    "__v": 0,
    "createdAt": "2026-07-20T10:01:30.815Z",
    "isFallback": false,
    "reason": "Perfect Attendance: 0 PSL, 0 Half-Days, 0 LWP",
    "tier": 1,
    "updatedAt": "2026-07-20T10:01:30.815Z"
  },
  {
    "_id": "6a5df1fb7a6effd18ee4086a",
    "employeeId": "6a20168d779aee60f9a25b9e",
    "month": 6,
    "year": 2026,
    "__v": 0,
    "createdAt": "2026-07-20T10:01:31.624Z",
    "isFallback": false,
    "reason": "Perfect Attendance: 0 PSL, 0 Half-Days, 0 LWP",
    "tier": 1,
    "updatedAt": "2026-07-20T10:01:31.624Z"
  },
  {
    "_id": "6a5df1fb7a6effd18ee4086c",
    "month": 6,
    "employeeId": "6a20584d9e4df9a820c22ab5",
    "year": 2026,
    "__v": 0,
    "createdAt": "2026-07-20T10:01:32.019Z",
    "isFallback": false,
    "reason": "Perfect Attendance: 0 PSL, 0 Half-Days, 0 LWP",
    "tier": 1,
    "updatedAt": "2026-07-20T10:01:32.019Z"
  },
  {
    "_id": "6a5df1fc7a6effd18ee4086e",
    "month": 6,
    "year": 2026,
    "employeeId": "6a210c699e4df9a820c23111",
    "__v": 0,
    "createdAt": "2026-07-20T10:01:32.360Z",
    "isFallback": false,
    "reason": "Perfect Attendance: 0 PSL, 0 Half-Days, 0 LWP",
    "tier": 1,
    "updatedAt": "2026-07-20T10:01:32.360Z"
  },
  {
    "_id": "6a5df1fc7a6effd18ee40870",
    "employeeId": "6a1d1e3271523c75c540fb51",
    "year": 2026,
    "month": 6,
    "__v": 0,
    "createdAt": "2026-07-20T10:01:32.712Z",
    "isFallback": false,
    "reason": "Perfect Attendance: 0 PSL, 0 Half-Days, 0 LWP",
    "tier": 1,
    "updatedAt": "2026-07-20T10:01:32.712Z"
  },
  {
    "_id": "6a5df1fc7a6effd18ee40872",
    "month": 6,
    "year": 2026,
    "employeeId": "6a1fcb409f42d83bb7635f57",
    "__v": 0,
    "createdAt": "2026-07-20T10:01:33.102Z",
    "isFallback": false,
    "reason": "Perfect Attendance: 0 PSL, 0 Half-Days, 0 LWP",
    "tier": 1,
    "updatedAt": "2026-07-20T10:01:33.102Z"
  },
  {
    "_id": "6a5df1fd7a6effd18ee40874",
    "month": 6,
    "employeeId": "6a2015e0779aee60f9a25b95",
    "year": 2026,
    "__v": 0,
    "createdAt": "2026-07-20T10:01:33.494Z",
    "isFallback": false,
    "reason": "Perfect Attendance: 0 PSL, 0 Half-Days, 0 LWP",
    "tier": 1,
    "updatedAt": "2026-07-20T10:01:33.494Z"
  },
  {
    "_id": "6a5df1fd7a6effd18ee40876",
    "employeeId": "6a2017ee779aee60f9a25c11",
    "month": 6,
    "year": 2026,
    "__v": 0,
    "createdAt": "2026-07-20T10:01:33.919Z",
    "isFallback": false,
    "reason": "Perfect Attendance: 0 PSL, 0 Half-Days, 0 LWP",
    "tier": 1,
    "updatedAt": "2026-07-20T10:01:33.919Z"
  },
  {
    "_id": "6a5df1fe7a6effd18ee40878",
    "employeeId": "6a201e189e4df9a820c22535",
    "month": 6,
    "year": 2026,
    "__v": 0,
    "createdAt": "2026-07-20T10:01:34.449Z",
    "isFallback": false,
    "reason": "Perfect Attendance: 0 PSL, 0 Half-Days, 0 LWP",
    "tier": 1,
    "updatedAt": "2026-07-20T10:01:34.449Z"
  },
  {
    "_id": "6a5df1fe7a6effd18ee4087a",
    "month": 6,
    "employeeId": "6a201f339e4df9a820c22627",
    "year": 2026,
    "__v": 0,
    "createdAt": "2026-07-20T10:01:34.867Z",
    "isFallback": false,
    "reason": "Perfect Attendance: 0 PSL, 0 Half-Days, 0 LWP",
    "tier": 1,
    "updatedAt": "2026-07-20T10:01:34.867Z"
  },
  {
    "_id": "6a5df1ff7a6effd18ee4087c",
    "month": 6,
    "employeeId": "6a21067d9e4df9a820c22e3d",
    "year": 2026,
    "__v": 0,
    "createdAt": "2026-07-20T10:01:35.301Z",
    "isFallback": false,
    "reason": "Perfect Attendance: 0 PSL, 0 Half-Days, 0 LWP",
    "tier": 1,
    "updatedAt": "2026-07-20T10:01:35.301Z"
  },
  {
    "_id": "6a5df1ff7a6effd18ee4087e",
    "employeeId": "6a21089b9e4df9a820c22f0f",
    "month": 6,
    "year": 2026,
    "__v": 0,
    "createdAt": "2026-07-20T10:01:35.655Z",
    "isFallback": false,
    "reason": "Perfect Attendance: 0 PSL, 0 Half-Days, 0 LWP",
    "tier": 1,
    "updatedAt": "2026-07-20T10:01:35.655Z"
  },
  {
    "_id": "6a5df2007a6effd18ee40880",
    "employeeId": "6a1d1e2f71523c75c540fb35",
    "year": 2026,
    "month": 6,
    "__v": 0,
    "createdAt": "2026-07-20T10:01:36.160Z",
    "isFallback": false,
    "reason": "Perfect Attendance: 0 PSL, 0 Half-Days, 0 LWP",
    "tier": 1,
    "updatedAt": "2026-07-20T10:01:36.160Z"
  },
  {
    "_id": "6a5df2007a6effd18ee40882",
    "month": 6,
    "year": 2026,
    "employeeId": "6a1d1e3071523c75c540fb41",
    "__v": 0,
    "createdAt": "2026-07-20T10:01:36.642Z",
    "isFallback": false,
    "reason": "Perfect Attendance: 0 PSL, 0 Half-Days, 0 LWP",
    "tier": 1,
    "updatedAt": "2026-07-20T10:01:36.642Z"
  },
  {
    "_id": "6a5df2007a6effd18ee40884",
    "month": 6,
    "employeeId": "6a200920311c45376c8e6beb",
    "year": 2026,
    "__v": 0,
    "createdAt": "2026-07-20T10:01:37.005Z",
    "isFallback": false,
    "reason": "Perfect Attendance: 0 PSL, 0 Half-Days, 0 LWP",
    "tier": 1,
    "updatedAt": "2026-07-20T10:01:37.005Z"
  },
  {
    "_id": "6a5df2017a6effd18ee40886",
    "employeeId": "6a201edd9e4df9a820c225fb",
    "year": 2026,
    "month": 6,
    "__v": 0,
    "createdAt": "2026-07-20T10:01:37.483Z",
    "isFallback": false,
    "reason": "Perfect Attendance: 0 PSL, 0 Half-Days, 0 LWP",
    "tier": 1,
    "updatedAt": "2026-07-20T10:01:37.483Z"
  },
  {
    "_id": "6a5df2017a6effd18ee40888",
    "month": 6,
    "employeeId": "6a210da89e4df9a820c231e1",
    "year": 2026,
    "__v": 0,
    "createdAt": "2026-07-20T10:01:38.035Z",
    "isFallback": false,
    "reason": "Perfect Attendance: 0 PSL, 0 Half-Days, 0 LWP",
    "tier": 1,
    "updatedAt": "2026-07-20T10:01:38.035Z"
  },
  {
    "_id": "6a5df2027a6effd18ee4088a",
    "month": 6,
    "year": 2026,
    "employeeId": "6a1d1e3171523c75c540fb49",
    "__v": 0,
    "createdAt": "2026-07-20T10:01:38.424Z",
    "isFallback": false,
    "reason": "Perfect Attendance: 0 PSL, 0 Half-Days, 0 LWP",
    "tier": 1,
    "updatedAt": "2026-07-20T10:01:38.424Z"
  },
  {
    "_id": "6a5df2027a6effd18ee4088c",
    "employeeId": "6a1fd4ce9f42d83bb763668c",
    "year": 2026,
    "month": 6,
    "__v": 0,
    "createdAt": "2026-07-20T10:01:38.773Z",
    "isFallback": false,
    "reason": "Perfect Attendance: 0 PSL, 0 Half-Days, 0 LWP",
    "tier": 1,
    "updatedAt": "2026-07-20T10:01:38.773Z"
  },
  {
    "_id": "6a5df2037a6effd18ee4088e",
    "employeeId": "6a1ff77b9f42d83bb763779e",
    "year": 2026,
    "month": 6,
    "__v": 0,
    "createdAt": "2026-07-20T10:01:39.162Z",
    "isFallback": false,
    "reason": "Perfect Attendance: 0 PSL, 0 Half-Days, 0 LWP",
    "tier": 1,
    "updatedAt": "2026-07-20T10:01:39.162Z"
  },
  {
    "_id": "6a5df2037a6effd18ee40890",
    "employeeId": "6a2004ae311c45376c8e6b6f",
    "year": 2026,
    "month": 6,
    "__v": 0,
    "createdAt": "2026-07-20T10:01:39.515Z",
    "isFallback": false,
    "reason": "Perfect Attendance: 0 PSL, 0 Half-Days, 0 LWP",
    "tier": 1,
    "updatedAt": "2026-07-20T10:01:39.515Z"
  },
  {
    "_id": "6a5df2037a6effd18ee40892",
    "month": 6,
    "year": 2026,
    "employeeId": "6a20089f311c45376c8e6be2",
    "__v": 0,
    "createdAt": "2026-07-20T10:01:39.965Z",
    "isFallback": false,
    "reason": "Perfect Attendance: 0 PSL, 0 Half-Days, 0 LWP",
    "tier": 1,
    "updatedAt": "2026-07-20T10:01:39.965Z"
  },
  {
    "_id": "6a5df2047a6effd18ee40894",
    "employeeId": "6a201e289e4df9a820c22540",
    "year": 2026,
    "month": 6,
    "__v": 0,
    "createdAt": "2026-07-20T10:01:40.327Z",
    "isFallback": false,
    "reason": "Perfect Attendance: 0 PSL, 0 Half-Days, 0 LWP",
    "tier": 1,
    "updatedAt": "2026-07-20T10:01:40.327Z"
  },
  {
    "_id": "6a5df2047a6effd18ee40896",
    "employeeId": "6a200a57311c45376c8e6bf4",
    "year": 2026,
    "month": 6,
    "__v": 0,
    "createdAt": "2026-07-20T10:01:40.835Z",
    "isFallback": false,
    "reason": "Perfect Attendance: 0 PSL, 0 Half-Days, 0 LWP",
    "tier": 1,
    "updatedAt": "2026-07-20T10:01:40.835Z"
  },
  {
    "_id": "6a5df2057a6effd18ee40898",
    "employeeId": "6a201b0d779aee60f9a25cc7",
    "month": 6,
    "year": 2026,
    "__v": 0,
    "createdAt": "2026-07-20T10:01:41.429Z",
    "isFallback": false,
    "reason": "Perfect Attendance: 0 PSL, 0 Half-Days, 0 LWP",
    "tier": 1,
    "updatedAt": "2026-07-20T10:01:41.429Z"
  },
  {
    "_id": "6a5df2057a6effd18ee4089a",
    "month": 6,
    "year": 2026,
    "employeeId": "6a21640a1d3fe393896fe5cc",
    "__v": 0,
    "createdAt": "2026-07-20T10:01:41.855Z",
    "isFallback": false,
    "reason": "Perfect Attendance: 0 PSL, 0 Half-Days, 0 LWP",
    "tier": 1,
    "updatedAt": "2026-07-20T10:01:41.855Z"
  },
  {
    "_id": "6a5df2067a6effd18ee4089c",
    "month": 6,
    "employeeId": "6a1d1e3171523c75c540fb4d",
    "year": 2026,
    "__v": 0,
    "createdAt": "2026-07-20T10:01:42.346Z",
    "isFallback": false,
    "reason": "Perfect Attendance: 0 PSL, 0 Half-Days, 0 LWP",
    "tier": 1,
    "updatedAt": "2026-07-20T10:01:42.346Z"
  },
  {
    "_id": "6a5df2077a6effd18ee4089e",
    "employeeId": "6a2013b8943b2ce58f2ba723",
    "month": 6,
    "year": 2026,
    "__v": 0,
    "createdAt": "2026-07-20T10:01:43.138Z",
    "isFallback": false,
    "reason": "Perfect Attendance: 0 PSL, 0 Half-Days, 0 LWP",
    "tier": 1,
    "updatedAt": "2026-07-20T10:01:43.138Z"
  },
  {
    "_id": "6a5df2077a6effd18ee408a0",
    "month": 6,
    "year": 2026,
    "employeeId": "6a201c16779aee60f9a25eca",
    "__v": 0,
    "createdAt": "2026-07-20T10:01:43.991Z",
    "isFallback": false,
    "reason": "Perfect Attendance: 0 PSL, 0 Half-Days, 0 LWP",
    "tier": 1,
    "updatedAt": "2026-07-20T10:01:43.991Z"
  },
  {
    "_id": "6a5df2087a6effd18ee408a2",
    "month": 6,
    "year": 2026,
    "employeeId": "6a2107b79e4df9a820c22ee8",
    "__v": 0,
    "createdAt": "2026-07-20T10:01:44.596Z",
    "isFallback": false,
    "reason": "Perfect Attendance: 0 PSL, 0 Half-Days, 0 LWP",
    "tier": 1,
    "updatedAt": "2026-07-20T10:01:44.658Z"
  },
  {
    "_id": "6a5df2097a6effd18ee408a4",
    "employeeId": "6a2119599e4df9a820c23377",
    "month": 6,
    "year": 2026,
    "__v": 0,
    "createdAt": "2026-07-20T10:01:45.138Z",
    "isFallback": false,
    "reason": "Perfect Attendance: 0 PSL, 0 Half-Days, 0 LWP",
    "tier": 1,
    "updatedAt": "2026-07-20T10:01:45.342Z"
  },
  {
    "_id": "6a5df2097a6effd18ee408a6",
    "employeeId": "6a226501e30358b77365b1d8",
    "year": 2026,
    "month": 6,
    "__v": 0,
    "createdAt": "2026-07-20T10:01:45.690Z",
    "isFallback": false,
    "reason": "Perfect Attendance: 0 PSL, 0 Half-Days, 0 LWP",
    "tier": 1,
    "updatedAt": "2026-07-20T10:01:45.690Z"
  },
  {
    "_id": "6a5df2097a6effd18ee408a8",
    "employeeId": "6a1d1e3271523c75c540fb55",
    "month": 6,
    "year": 2026,
    "__v": 0,
    "createdAt": "2026-07-20T10:01:46.022Z",
    "isFallback": false,
    "reason": "Perfect Attendance: 0 PSL, 0 Half-Days, 0 LWP",
    "tier": 1,
    "updatedAt": "2026-07-20T10:01:46.060Z"
  },
  {
    "_id": "6a5df20a7a6effd18ee408aa",
    "month": 6,
    "year": 2026,
    "employeeId": "6a1d1e3271523c75c540fb59",
    "__v": 0,
    "createdAt": "2026-07-20T10:01:46.480Z",
    "isFallback": false,
    "reason": "Perfect Attendance: 0 PSL, 0 Half-Days, 0 LWP",
    "tier": 1,
    "updatedAt": "2026-07-20T10:01:46.526Z"
  },
  {
    "_id": "6a5df20a7a6effd18ee408ac",
    "month": 6,
    "year": 2026,
    "employeeId": "6a20052a311c45376c8e6b78",
    "__v": 0,
    "createdAt": "2026-07-20T10:01:46.830Z",
    "isFallback": false,
    "reason": "Perfect Attendance: 0 PSL, 0 Half-Days, 0 LWP",
    "tier": 1,
    "updatedAt": "2026-07-20T10:01:46.914Z"
  },
  {
    "_id": "6a5df20b7a6effd18ee408af",
    "month": 6,
    "year": 2026,
    "employeeId": "6a20189d779aee60f9a25c1a",
    "__v": 0,
    "createdAt": "2026-07-20T10:01:47.311Z",
    "isFallback": false,
    "reason": "Perfect Attendance: 0 PSL, 0 Half-Days, 0 LWP",
    "tier": 1,
    "updatedAt": "2026-07-20T10:01:47.311Z"
  },
  {
    "_id": "6a5df20b7a6effd18ee408b1",
    "employeeId": "6a210b329e4df9a820c230c2",
    "year": 2026,
    "month": 6,
    "__v": 0,
    "createdAt": "2026-07-20T10:01:47.822Z",
    "isFallback": false,
    "reason": "Perfect Attendance: 0 PSL, 0 Half-Days, 0 LWP",
    "tier": 1,
    "updatedAt": "2026-07-20T10:01:47.904Z"
  },
  {
    "_id": "6a5df20c7a6effd18ee408b3",
    "employeeId": "6a210e119e4df9a820c231ea",
    "year": 2026,
    "month": 6,
    "__v": 0,
    "createdAt": "2026-07-20T10:01:48.322Z",
    "isFallback": false,
    "reason": "Perfect Attendance: 0 PSL, 0 Half-Days, 0 LWP",
    "tier": 1,
    "updatedAt": "2026-07-20T10:01:48.440Z"
  },
  {
    "_id": "6a5df20c7a6effd18ee408b5",
    "month": 6,
    "year": 2026,
    "employeeId": "6a201e0ab1c4018e58627ab8",
    "__v": 0,
    "createdAt": "2026-07-20T10:01:48.718Z",
    "isFallback": false,
    "reason": "Perfect Attendance: 0 PSL, 0 Half-Days, 0 LWP",
    "tier": 1,
    "updatedAt": "2026-07-20T10:01:48.815Z"
  },
  {
    "_id": "6a5df20d7a6effd18ee408b7",
    "month": 6,
    "year": 2026,
    "employeeId": "6a1d1e3371523c75c540fb5d",
    "__v": 0,
    "createdAt": "2026-07-20T10:01:49.173Z",
    "isFallback": false,
    "reason": "Perfect Attendance: 0 PSL, 0 Half-Days, 0 LWP",
    "tier": 1,
    "updatedAt": "2026-07-20T10:01:49.269Z"
  },
  {
    "_id": "6a5df20d7a6effd18ee408b9",
    "month": 6,
    "year": 2026,
    "employeeId": "6a2007ca311c45376c8e6bd0",
    "__v": 0,
    "createdAt": "2026-07-20T10:01:49.573Z",
    "isFallback": false,
    "reason": "Perfect Attendance: 0 PSL, 0 Half-Days, 0 LWP",
    "tier": 1,
    "updatedAt": "2026-07-20T10:01:49.630Z"
  },
  {
    "_id": "6a5df20d7a6effd18ee408bb",
    "employeeId": "6a200820311c45376c8e6bd9",
    "month": 6,
    "year": 2026,
    "__v": 0,
    "createdAt": "2026-07-20T10:01:49.952Z",
    "isFallback": false,
    "reason": "Perfect Attendance: 0 PSL, 0 Half-Days, 0 LWP",
    "tier": 1,
    "updatedAt": "2026-07-20T10:01:50.026Z"
  },
  {
    "_id": "6a5df20e7a6effd18ee408bd",
    "employeeId": "6a201bf1779aee60f9a25db2",
    "month": 6,
    "year": 2026,
    "__v": 0,
    "createdAt": "2026-07-20T10:01:50.347Z",
    "isFallback": false,
    "reason": "Perfect Attendance: 0 PSL, 0 Half-Days, 0 LWP",
    "tier": 1,
    "updatedAt": "2026-07-20T10:01:50.389Z"
  },
  {
    "_id": "6a5df20e7a6effd18ee408bf",
    "employeeId": "6a201c29779aee60f9a25edc",
    "month": 6,
    "year": 2026,
    "__v": 0,
    "createdAt": "2026-07-20T10:01:50.689Z",
    "isFallback": false,
    "reason": "Perfect Attendance: 0 PSL, 0 Half-Days, 0 LWP",
    "tier": 1,
    "updatedAt": "2026-07-20T10:01:50.748Z"
  },
  {
    "_id": "6a5df20e7a6effd18ee408c1",
    "employeeId": "6a201cc9779aee60f9a25fc1",
    "year": 2026,
    "month": 6,
    "__v": 0,
    "createdAt": "2026-07-20T10:01:51.049Z",
    "isFallback": false,
    "reason": "Perfect Attendance: 0 PSL, 0 Half-Days, 0 LWP",
    "tier": 1,
    "updatedAt": "2026-07-20T10:01:51.095Z"
  },
  {
    "_id": "6a5df20f7a6effd18ee408c3",
    "employeeId": "6a210ca19e4df9a820c2312f",
    "month": 6,
    "year": 2026,
    "__v": 0,
    "createdAt": "2026-07-20T10:01:51.524Z",
    "isFallback": false,
    "reason": "Perfect Attendance: 0 PSL, 0 Half-Days, 0 LWP",
    "tier": 1,
    "updatedAt": "2026-07-20T10:01:51.561Z"
  },
  {
    "_id": "6a5df20f7a6effd18ee408c5",
    "month": 6,
    "year": 2026,
    "employeeId": "6a201bf9779aee60f9a25e42",
    "__v": 0,
    "createdAt": "2026-07-20T10:01:51.888Z",
    "isFallback": false,
    "reason": "Perfect Attendance: 0 PSL, 0 Half-Days, 0 LWP",
    "tier": 1,
    "updatedAt": "2026-07-20T10:01:51.935Z"
  },
  {
    "_id": "6a5df2107a6effd18ee408c7",
    "employeeId": "6a201cf5b1c4018e586279cc",
    "year": 2026,
    "month": 6,
    "__v": 0,
    "createdAt": "2026-07-20T10:01:52.270Z",
    "isFallback": false,
    "reason": "Perfect Attendance: 0 PSL, 0 Half-Days, 0 LWP",
    "tier": 1,
    "updatedAt": "2026-07-20T10:01:52.350Z"
  },
  {
    "_id": "6a5df2107a6effd18ee408c9",
    "employeeId": "6a1d1e2e71523c75c540fb31",
    "year": 2026,
    "month": 6,
    "__v": 0,
    "createdAt": "2026-07-20T10:01:52.957Z",
    "isFallback": false,
    "reason": "Perfect Attendance: 0 PSL, 0 Half-Days, 0 LWP",
    "tier": 1,
    "updatedAt": "2026-07-20T10:01:53.175Z"
  },
  {
    "_id": "6a5df2117a6effd18ee408cb",
    "month": 6,
    "year": 2026,
    "employeeId": "6a1d1e3071523c75c540fb39",
    "__v": 0,
    "createdAt": "2026-07-20T10:01:53.480Z",
    "isFallback": false,
    "reason": "Perfect Attendance: 0 PSL, 0 Half-Days, 0 LWP",
    "tier": 1,
    "updatedAt": "2026-07-20T10:01:53.564Z"
  },
  {
    "_id": "6a5df2117a6effd18ee408cd",
    "employeeId": "6a201c55779aee60f9a25f46",
    "year": 2026,
    "month": 6,
    "__v": 0,
    "createdAt": "2026-07-20T10:01:53.822Z",
    "isFallback": false,
    "reason": "Perfect Attendance: 0 PSL, 0 Half-Days, 0 LWP",
    "tier": 1,
    "updatedAt": "2026-07-20T10:01:53.917Z"
  },
  {
    "_id": "6a5df2127a6effd18ee408cf",
    "employeeId": "6a21528f453d791e72eae17b",
    "month": 6,
    "year": 2026,
    "__v": 0,
    "createdAt": "2026-07-20T10:01:54.166Z",
    "isFallback": false,
    "reason": "Perfect Attendance: 0 PSL, 0 Half-Days, 0 LWP",
    "tier": 1,
    "updatedAt": "2026-07-20T10:01:54.247Z"
  },
  {
    "_id": "6a5df2127a6effd18ee408d1",
    "employeeId": "6a1d1e3371523c75c540fb61",
    "year": 2026,
    "month": 6,
    "__v": 0,
    "createdAt": "2026-07-20T10:01:54.495Z",
    "isFallback": false,
    "reason": "Perfect Attendance: 0 PSL, 0 Half-Days, 0 LWP",
    "tier": 1,
    "updatedAt": "2026-07-20T10:01:54.681Z"
  },
  {
    "_id": "6a5df2127a6effd18ee408d3",
    "month": 6,
    "year": 2026,
    "employeeId": "6a201d8fb1c4018e58627a12",
    "__v": 0,
    "createdAt": "2026-07-20T10:01:54.895Z",
    "isFallback": false,
    "reason": "Perfect Attendance: 0 PSL, 0 Half-Days, 0 LWP",
    "tier": 1,
    "updatedAt": "2026-07-20T10:01:55.140Z"
  },
  {
    "_id": "6a5df2137a6effd18ee408d5",
    "employeeId": "6a210aaf9e4df9a820c2308b",
    "month": 6,
    "year": 2026,
    "__v": 0,
    "createdAt": "2026-07-20T10:01:55.589Z",
    "isFallback": false,
    "reason": "Perfect Attendance: 0 PSL, 0 Half-Days, 0 LWP",
    "tier": 1,
    "updatedAt": "2026-07-20T10:01:55.757Z"
  },
  {
    "_id": "6a5df2137a6effd18ee408d7",
    "employeeId": "6a210bcf9e4df9a820c230f2",
    "year": 2026,
    "month": 6,
    "__v": 0,
    "createdAt": "2026-07-20T10:01:56.014Z",
    "isFallback": false,
    "reason": "Perfect Attendance: 0 PSL, 0 Half-Days, 0 LWP",
    "tier": 1,
    "updatedAt": "2026-07-20T10:01:56.250Z"
  },
  {
    "_id": "6a5df2147a6effd18ee408d9",
    "employeeId": "6a20154d779aee60f9a25b8c",
    "year": 2026,
    "month": 6,
    "__v": 0,
    "createdAt": "2026-07-20T10:01:56.791Z",
    "isFallback": false,
    "reason": "Perfect Attendance: 0 PSL, 0 Half-Days, 0 LWP",
    "tier": 1,
    "updatedAt": "2026-07-20T10:01:56.920Z"
  },
  {
    "_id": "6a5df2157a6effd18ee408db",
    "employeeId": "6a201ec19e4df9a820c225b1",
    "year": 2026,
    "month": 6,
    "__v": 0,
    "createdAt": "2026-07-20T10:01:57.411Z",
    "isFallback": false,
    "reason": "Perfect Attendance: 0 PSL, 0 Half-Days, 0 LWP",
    "tier": 1,
    "updatedAt": "2026-07-20T10:01:57.577Z"
  },
  {
    "_id": "6a5df2157a6effd18ee408dd",
    "month": 6,
    "year": 2026,
    "employeeId": "6a210c199e4df9a820c23108",
    "__v": 0,
    "createdAt": "2026-07-20T10:01:57.986Z",
    "isFallback": false,
    "reason": "Perfect Attendance: 0 PSL, 0 Half-Days, 0 LWP",
    "tier": 1,
    "updatedAt": "2026-07-20T10:01:58.285Z"
  },
  {
    "_id": "6a5df2167a6effd18ee408df",
    "employeeId": "6a210d159e4df9a820c2319c",
    "month": 6,
    "year": 2026,
    "__v": 0,
    "createdAt": "2026-07-20T10:01:58.408Z",
    "isFallback": false,
    "reason": "Perfect Attendance: 0 PSL, 0 Half-Days, 0 LWP",
    "tier": 1,
    "updatedAt": "2026-07-20T10:01:58.408Z"
  },
  {
    "_id": "6a5df2167a6effd18ee408e1",
    "employeeId": "6a2129579e4df9a820c23444",
    "month": 6,
    "year": 2026,
    "__v": 0,
    "createdAt": "2026-07-20T10:01:58.757Z",
    "isFallback": false,
    "reason": "Perfect Attendance: 0 PSL, 0 Half-Days, 0 LWP",
    "tier": 1,
    "updatedAt": "2026-07-20T10:01:58.796Z"
  },
  {
    "_id": "6a5df2177a6effd18ee408e3",
    "employeeId": "6a2164791d3fe393896fe5e9",
    "year": 2026,
    "month": 6,
    "__v": 0,
    "createdAt": "2026-07-20T10:01:59.293Z",
    "isFallback": false,
    "reason": "Perfect Attendance: 0 PSL, 0 Half-Days, 0 LWP",
    "tier": 1,
    "updatedAt": "2026-07-20T10:01:59.337Z"
  },
  {
    "_id": "6a5df2177a6effd18ee408e5",
    "month": 6,
    "employeeId": "6a2264afe30358b77365b103",
    "year": 2026,
    "__v": 0,
    "createdAt": "2026-07-20T10:01:59.784Z",
    "isFallback": false,
    "reason": "Perfect Attendance: 0 PSL, 0 Half-Days, 0 LWP",
    "tier": 1,
    "updatedAt": "2026-07-20T10:01:59.817Z"
  },
  {
    "_id": "6a5df2187a6effd18ee408e7",
    "month": 6,
    "year": 2026,
    "employeeId": "6a226554e30358b77365b48b",
    "__v": 0,
    "createdAt": "2026-07-20T10:02:00.164Z",
    "isFallback": false,
    "reason": "Perfect Attendance: 0 PSL, 0 Half-Days, 0 LWP",
    "tier": 1,
    "updatedAt": "2026-07-20T10:02:00.176Z"
  }
]